package appinventor.ai_prafulmathur95.whereismycar;

import com.google.appinventor.components.runtime.ActivityStarter;
import com.google.appinventor.components.runtime.Button;
import com.google.appinventor.components.runtime.Canvas;
import com.google.appinventor.components.runtime.Component;
import com.google.appinventor.components.runtime.EventDispatcher;
import com.google.appinventor.components.runtime.Form;
import com.google.appinventor.components.runtime.HorizontalArrangement;
import com.google.appinventor.components.runtime.Label;
import com.google.appinventor.components.runtime.LocationSensor;
import com.google.appinventor.components.runtime.TinyDB;
import com.google.appinventor.components.runtime.util.RetValManager;
import com.google.youngandroid.runtime;
import gnu.expr.ModuleBody;
import gnu.expr.ModuleInfo;
import gnu.expr.ModuleMethod;
import gnu.kawa.functions.Format;
import gnu.lists.Consumer;
import gnu.lists.FString;
import gnu.lists.LList;
import gnu.lists.Pair;
import gnu.lists.PairWithPosition;
import gnu.lists.VoidConsumer;
import gnu.mapping.CallContext;
import gnu.mapping.Environment;
import gnu.mapping.Procedure;
import gnu.mapping.PropertySet;
import gnu.mapping.SimpleSymbol;
import gnu.mapping.Symbol;
import gnu.mapping.Values;
import gnu.math.IntNum;
import kawa.lib.lists;
import kawa.lib.misc;
import kawa.lib.strings;
import kawa.standard.Scheme;

public class Screen1
  extends Form
  implements Runnable
{
  static final SimpleSymbol Lit0 = (SimpleSymbol)new SimpleSymbol("Screen1").readResolve();
  static final SimpleSymbol Lit1;
  static final SimpleSymbol Lit10;
  static final SimpleSymbol Lit100;
  static final SimpleSymbol Lit101;
  static final PairWithPosition Lit102;
  static final PairWithPosition Lit103;
  static final PairWithPosition Lit104;
  static final SimpleSymbol Lit105;
  static final SimpleSymbol Lit106;
  static final FString Lit107;
  static final SimpleSymbol Lit108;
  static final IntNum Lit109;
  static final SimpleSymbol Lit11;
  static final FString Lit110;
  static final FString Lit111;
  static final SimpleSymbol Lit112;
  static final FString Lit113;
  static final FString Lit114;
  static final SimpleSymbol Lit115;
  static final IntNum Lit116;
  static final FString Lit117;
  static final FString Lit118;
  static final IntNum Lit119;
  static final SimpleSymbol Lit12;
  static final FString Lit120;
  static final FString Lit121;
  static final SimpleSymbol Lit122;
  static final FString Lit123;
  static final FString Lit124;
  static final SimpleSymbol Lit125;
  static final IntNum Lit126;
  static final FString Lit127;
  static final FString Lit128;
  static final IntNum Lit129;
  static final SimpleSymbol Lit13;
  static final FString Lit130;
  static final FString Lit131;
  static final SimpleSymbol Lit132;
  static final IntNum Lit133;
  static final FString Lit134;
  static final FString Lit135;
  static final IntNum Lit136;
  static final FString Lit137;
  static final FString Lit138;
  static final FString Lit139;
  static final SimpleSymbol Lit14;
  static final PairWithPosition Lit140;
  static final PairWithPosition Lit141;
  static final SimpleSymbol Lit142;
  static final SimpleSymbol Lit143;
  static final PairWithPosition Lit144;
  static final SimpleSymbol Lit145;
  static final PairWithPosition Lit146;
  static final SimpleSymbol Lit147;
  static final FString Lit148;
  static final FString Lit149;
  static final SimpleSymbol Lit15;
  static final SimpleSymbol Lit150;
  static final SimpleSymbol Lit151;
  static final FString Lit152;
  static final SimpleSymbol Lit153;
  static final SimpleSymbol Lit154;
  static final SimpleSymbol Lit155;
  static final FString Lit156;
  static final FString Lit157;
  static final FString Lit158;
  static final FString Lit159;
  static final SimpleSymbol Lit16;
  static final FString Lit160;
  static final FString Lit161;
  static final FString Lit162;
  static final SimpleSymbol Lit163;
  static final SimpleSymbol Lit164;
  static final SimpleSymbol Lit165;
  static final SimpleSymbol Lit166;
  static final SimpleSymbol Lit167;
  static final SimpleSymbol Lit168;
  static final SimpleSymbol Lit169;
  static final SimpleSymbol Lit17;
  static final SimpleSymbol Lit170;
  static final SimpleSymbol Lit171;
  static final SimpleSymbol Lit172;
  static final SimpleSymbol Lit173;
  static final SimpleSymbol Lit174;
  static final SimpleSymbol Lit175 = (SimpleSymbol)new SimpleSymbol("any").readResolve();
  static final SimpleSymbol Lit18;
  static final SimpleSymbol Lit19;
  static final SimpleSymbol Lit2;
  static final PairWithPosition Lit20;
  static final PairWithPosition Lit21;
  static final IntNum Lit22;
  static final PairWithPosition Lit23;
  static final SimpleSymbol Lit24;
  static final SimpleSymbol Lit25;
  static final SimpleSymbol Lit26;
  static final SimpleSymbol Lit27;
  static final PairWithPosition Lit28;
  static final SimpleSymbol Lit29;
  static final SimpleSymbol Lit3;
  static final SimpleSymbol Lit30;
  static final PairWithPosition Lit31;
  static final SimpleSymbol Lit32;
  static final SimpleSymbol Lit33;
  static final SimpleSymbol Lit34;
  static final FString Lit35;
  static final SimpleSymbol Lit36;
  static final SimpleSymbol Lit37;
  static final IntNum Lit38;
  static final SimpleSymbol Lit39;
  static final SimpleSymbol Lit4;
  static final IntNum Lit40;
  static final FString Lit41;
  static final FString Lit42;
  static final SimpleSymbol Lit43;
  static final FString Lit44;
  static final FString Lit45;
  static final SimpleSymbol Lit46;
  static final IntNum Lit47;
  static final FString Lit48;
  static final FString Lit49;
  static final SimpleSymbol Lit5;
  static final SimpleSymbol Lit50;
  static final SimpleSymbol Lit51;
  static final IntNum Lit52;
  static final SimpleSymbol Lit53;
  static final IntNum Lit54;
  static final SimpleSymbol Lit55;
  static final IntNum Lit56;
  static final FString Lit57;
  static final FString Lit58;
  static final SimpleSymbol Lit59;
  static final SimpleSymbol Lit6;
  static final FString Lit60;
  static final FString Lit61;
  static final SimpleSymbol Lit62;
  static final IntNum Lit63;
  static final IntNum Lit64;
  static final FString Lit65;
  static final FString Lit66;
  static final SimpleSymbol Lit67;
  static final IntNum Lit68;
  static final IntNum Lit69;
  static final IntNum Lit7;
  static final FString Lit70;
  static final FString Lit71;
  static final SimpleSymbol Lit72;
  static final FString Lit73;
  static final FString Lit74;
  static final SimpleSymbol Lit75;
  static final IntNum Lit76;
  static final FString Lit77;
  static final FString Lit78;
  static final SimpleSymbol Lit79;
  static final SimpleSymbol Lit8;
  static final IntNum Lit80;
  static final FString Lit81;
  static final FString Lit82;
  static final SimpleSymbol Lit83;
  static final IntNum Lit84;
  static final FString Lit85;
  static final FString Lit86;
  static final SimpleSymbol Lit87;
  static final IntNum Lit88;
  static final FString Lit89;
  static final SimpleSymbol Lit9;
  static final FString Lit90;
  static final SimpleSymbol Lit91;
  static final FString Lit92;
  static final FString Lit93;
  static final SimpleSymbol Lit94;
  static final IntNum Lit95;
  static final SimpleSymbol Lit96;
  static final FString Lit97;
  static final SimpleSymbol Lit98;
  static final SimpleSymbol Lit99;
  public static Screen1 Screen1;
  static final ModuleMethod lambda$Fn1;
  static final ModuleMethod lambda$Fn10;
  static final ModuleMethod lambda$Fn11;
  static final ModuleMethod lambda$Fn12;
  static final ModuleMethod lambda$Fn13;
  static final ModuleMethod lambda$Fn14;
  static final ModuleMethod lambda$Fn15;
  static final ModuleMethod lambda$Fn16;
  static final ModuleMethod lambda$Fn17;
  static final ModuleMethod lambda$Fn18;
  static final ModuleMethod lambda$Fn19;
  static final ModuleMethod lambda$Fn2;
  static final ModuleMethod lambda$Fn20;
  static final ModuleMethod lambda$Fn21;
  static final ModuleMethod lambda$Fn22;
  static final ModuleMethod lambda$Fn23;
  static final ModuleMethod lambda$Fn24;
  static final ModuleMethod lambda$Fn25;
  static final ModuleMethod lambda$Fn26;
  static final ModuleMethod lambda$Fn27;
  static final ModuleMethod lambda$Fn28;
  static final ModuleMethod lambda$Fn29;
  static final ModuleMethod lambda$Fn3;
  static final ModuleMethod lambda$Fn30;
  static final ModuleMethod lambda$Fn31;
  static final ModuleMethod lambda$Fn32;
  static final ModuleMethod lambda$Fn33;
  static final ModuleMethod lambda$Fn34;
  static final ModuleMethod lambda$Fn35;
  static final ModuleMethod lambda$Fn36;
  static final ModuleMethod lambda$Fn37;
  static final ModuleMethod lambda$Fn38;
  static final ModuleMethod lambda$Fn39;
  static final ModuleMethod lambda$Fn4;
  static final ModuleMethod lambda$Fn40;
  static final ModuleMethod lambda$Fn41;
  static final ModuleMethod lambda$Fn42;
  static final ModuleMethod lambda$Fn43;
  static final ModuleMethod lambda$Fn44;
  static final ModuleMethod lambda$Fn45;
  static final ModuleMethod lambda$Fn5;
  static final ModuleMethod lambda$Fn6;
  static final ModuleMethod lambda$Fn7;
  static final ModuleMethod lambda$Fn8;
  static final ModuleMethod lambda$Fn9;
  public Boolean $Stdebug$Mnform$St;
  public final ModuleMethod $define;
  public ActivityStarter ActivityStarter1;
  public Canvas Canvas1;
  public Canvas Canvas2;
  public HorizontalArrangement HorizontalArrangement1;
  public HorizontalArrangement HorizontalArrangement2;
  public HorizontalArrangement HorizontalArrangement3;
  public HorizontalArrangement HorizontalArrangement4;
  public HorizontalArrangement HorizontalArrangement5;
  public HorizontalArrangement HorizontalArrangement6;
  public Label Label1;
  public Label Label11;
  public Label Label13;
  public Label Label2;
  public Label Label4;
  public Label Label6;
  public Label Label8;
  public Label Label9;
  public LocationSensor LocationSensor1;
  public final ModuleMethod LocationSensor1$LocationChanged;
  public Button RememberButton;
  public final ModuleMethod RememberButton$Click;
  public final ModuleMethod Screen1$Initialize;
  public TinyDB TinyDB1;
  public TinyDB TinyDB2;
  public TinyDB TinyDB3;
  public final ModuleMethod add$Mnto$Mncomponents;
  public final ModuleMethod add$Mnto$Mnevents;
  public final ModuleMethod add$Mnto$Mnform$Mndo$Mnafter$Mncreation;
  public final ModuleMethod add$Mnto$Mnform$Mnenvironment;
  public final ModuleMethod add$Mnto$Mnglobal$Mnvar$Mnenvironment;
  public final ModuleMethod add$Mnto$Mnglobal$Mnvars;
  public final ModuleMethod android$Mnlog$Mnform;
  public LList components$Mnto$Mncreate;
  public Label currentaddressdatalabel;
  public Label currentlatlabel;
  public Label currentlongLabel;
  public Button directionbutton;
  public final ModuleMethod directionbutton$Click;
  public final ModuleMethod dispatchEvent;
  public LList events$Mnto$Mnregister;
  public LList form$Mndo$Mnafter$Mncreation;
  public Environment form$Mnenvironment;
  public Symbol form$Mnname$Mnsymbol;
  public Environment global$Mnvar$Mnenvironment;
  public LList global$Mnvars$Mnto$Mncreate;
  public final ModuleMethod is$Mnbound$Mnin$Mnform$Mnenvironment;
  public final ModuleMethod lookup$Mnhandler;
  public final ModuleMethod lookup$Mnin$Mnform$Mnenvironment;
  public final ModuleMethod process$Mnexception;
  public Label rememberedLongLabel;
  public Label rememberedaddressdatalabel;
  public Label rememberedlatLabel;
  public final ModuleMethod send$Mnerror;
  
  static
  {
    Lit174 = (SimpleSymbol)new SimpleSymbol("lookup-handler").readResolve();
    Lit173 = (SimpleSymbol)new SimpleSymbol("dispatchEvent").readResolve();
    Lit172 = (SimpleSymbol)new SimpleSymbol("send-error").readResolve();
    Lit171 = (SimpleSymbol)new SimpleSymbol("add-to-form-do-after-creation").readResolve();
    Lit170 = (SimpleSymbol)new SimpleSymbol("add-to-global-vars").readResolve();
    Lit169 = (SimpleSymbol)new SimpleSymbol("add-to-components").readResolve();
    Lit168 = (SimpleSymbol)new SimpleSymbol("add-to-events").readResolve();
    Lit167 = (SimpleSymbol)new SimpleSymbol("add-to-global-var-environment").readResolve();
    Lit166 = (SimpleSymbol)new SimpleSymbol("is-bound-in-form-environment").readResolve();
    Lit165 = (SimpleSymbol)new SimpleSymbol("lookup-in-form-environment").readResolve();
    Lit164 = (SimpleSymbol)new SimpleSymbol("add-to-form-environment").readResolve();
    Lit163 = (SimpleSymbol)new SimpleSymbol("android-log-form").readResolve();
    Lit162 = new FString("com.google.appinventor.components.runtime.TinyDB");
    Lit161 = new FString("com.google.appinventor.components.runtime.TinyDB");
    Lit160 = new FString("com.google.appinventor.components.runtime.TinyDB");
    Lit159 = new FString("com.google.appinventor.components.runtime.TinyDB");
    Lit158 = new FString("com.google.appinventor.components.runtime.TinyDB");
    Lit157 = new FString("com.google.appinventor.components.runtime.TinyDB");
    Lit156 = new FString("com.google.appinventor.components.runtime.ActivityStarter");
    Lit155 = (SimpleSymbol)new SimpleSymbol("ActivityPackage").readResolve();
    Lit154 = (SimpleSymbol)new SimpleSymbol("ActivityClass").readResolve();
    Lit153 = (SimpleSymbol)new SimpleSymbol("Action").readResolve();
    Lit152 = new FString("com.google.appinventor.components.runtime.ActivityStarter");
    Lit151 = (SimpleSymbol)new SimpleSymbol("LocationChanged").readResolve();
    Lit150 = (SimpleSymbol)new SimpleSymbol("LocationSensor1$LocationChanged").readResolve();
    Lit149 = new FString("com.google.appinventor.components.runtime.LocationSensor");
    Lit148 = new FString("com.google.appinventor.components.runtime.LocationSensor");
    Lit147 = (SimpleSymbol)new SimpleSymbol("directionbutton$Click").readResolve();
    Object localObject = (SimpleSymbol)new SimpleSymbol("text").readResolve();
    Lit5 = (SimpleSymbol)localObject;
    Lit146 = PairWithPosition.make(localObject, PairWithPosition.make(Lit5, PairWithPosition.make(Lit5, PairWithPosition.make(Lit5, PairWithPosition.make(Lit5, PairWithPosition.make(Lit5, PairWithPosition.make(Lit5, PairWithPosition.make(Lit5, LList.Empty, "/tmp/1439383140418_0.797949561504734-0/youngandroidproject/../src/appinventor/ai_prafulmathur95/whereismycar/Screen1.yail", 1082396), "/tmp/1439383140418_0.797949561504734-0/youngandroidproject/../src/appinventor/ai_prafulmathur95/whereismycar/Screen1.yail", 1082391), "/tmp/1439383140418_0.797949561504734-0/youngandroidproject/../src/appinventor/ai_prafulmathur95/whereismycar/Screen1.yail", 1082386), "/tmp/1439383140418_0.797949561504734-0/youngandroidproject/../src/appinventor/ai_prafulmathur95/whereismycar/Screen1.yail", 1082381), "/tmp/1439383140418_0.797949561504734-0/youngandroidproject/../src/appinventor/ai_prafulmathur95/whereismycar/Screen1.yail", 1082376), "/tmp/1439383140418_0.797949561504734-0/youngandroidproject/../src/appinventor/ai_prafulmathur95/whereismycar/Screen1.yail", 1082371), "/tmp/1439383140418_0.797949561504734-0/youngandroidproject/../src/appinventor/ai_prafulmathur95/whereismycar/Screen1.yail", 1082366), "/tmp/1439383140418_0.797949561504734-0/youngandroidproject/../src/appinventor/ai_prafulmathur95/whereismycar/Screen1.yail", 1082360);
    Lit145 = (SimpleSymbol)new SimpleSymbol("StartActivity").readResolve();
    Lit144 = PairWithPosition.make(Lit5, PairWithPosition.make(Lit5, PairWithPosition.make(Lit5, PairWithPosition.make(Lit5, LList.Empty, "/tmp/1439383140418_0.797949561504734-0/youngandroidproject/../src/appinventor/ai_prafulmathur95/whereismycar/Screen1.yail", 1081921), "/tmp/1439383140418_0.797949561504734-0/youngandroidproject/../src/appinventor/ai_prafulmathur95/whereismycar/Screen1.yail", 1081916), "/tmp/1439383140418_0.797949561504734-0/youngandroidproject/../src/appinventor/ai_prafulmathur95/whereismycar/Screen1.yail", 1081911), "/tmp/1439383140418_0.797949561504734-0/youngandroidproject/../src/appinventor/ai_prafulmathur95/whereismycar/Screen1.yail", 1081905);
    Lit143 = (SimpleSymbol)new SimpleSymbol("DataUri").readResolve();
    Lit142 = (SimpleSymbol)new SimpleSymbol("ActivityStarter1").readResolve();
    Lit141 = PairWithPosition.make(Lit175, PairWithPosition.make(Lit175, LList.Empty, "/tmp/1439383140418_0.797949561504734-0/youngandroidproject/../src/appinventor/ai_prafulmathur95/whereismycar/Screen1.yail", 1081656), "/tmp/1439383140418_0.797949561504734-0/youngandroidproject/../src/appinventor/ai_prafulmathur95/whereismycar/Screen1.yail", 1081651);
    Lit140 = PairWithPosition.make(Lit175, PairWithPosition.make(Lit175, LList.Empty, "/tmp/1439383140418_0.797949561504734-0/youngandroidproject/../src/appinventor/ai_prafulmathur95/whereismycar/Screen1.yail", 1081505), "/tmp/1439383140418_0.797949561504734-0/youngandroidproject/../src/appinventor/ai_prafulmathur95/whereismycar/Screen1.yail", 1081500);
    Lit139 = new FString("com.google.appinventor.components.runtime.Button");
    Lit138 = new FString("com.google.appinventor.components.runtime.Button");
    Lit137 = new FString("com.google.appinventor.components.runtime.Label");
    localObject = new int[2];
    localObject[0] = -1;
    Lit136 = IntNum.make((int[])localObject);
    Lit135 = new FString("com.google.appinventor.components.runtime.Label");
    Lit134 = new FString("com.google.appinventor.components.runtime.Label");
    localObject = new int[2];
    localObject[0] = -1;
    Lit133 = IntNum.make((int[])localObject);
    Lit132 = (SimpleSymbol)new SimpleSymbol("Label13").readResolve();
    Lit131 = new FString("com.google.appinventor.components.runtime.Label");
    Lit130 = new FString("com.google.appinventor.components.runtime.Label");
    localObject = new int[2];
    localObject[0] = -1;
    Lit129 = IntNum.make((int[])localObject);
    Lit128 = new FString("com.google.appinventor.components.runtime.Label");
    Lit127 = new FString("com.google.appinventor.components.runtime.Label");
    localObject = new int[2];
    localObject[0] = -1;
    Lit126 = IntNum.make((int[])localObject);
    Lit125 = (SimpleSymbol)new SimpleSymbol("Label11").readResolve();
    Lit124 = new FString("com.google.appinventor.components.runtime.Label");
    Lit123 = new FString("com.google.appinventor.components.runtime.HorizontalArrangement");
    Lit122 = (SimpleSymbol)new SimpleSymbol("HorizontalArrangement4").readResolve();
    Lit121 = new FString("com.google.appinventor.components.runtime.HorizontalArrangement");
    Lit120 = new FString("com.google.appinventor.components.runtime.Label");
    localObject = new int[2];
    localObject[0] = -1;
    Lit119 = IntNum.make((int[])localObject);
    Lit118 = new FString("com.google.appinventor.components.runtime.Label");
    Lit117 = new FString("com.google.appinventor.components.runtime.Label");
    localObject = new int[2];
    localObject[0] = -1;
    Lit116 = IntNum.make((int[])localObject);
    Lit115 = (SimpleSymbol)new SimpleSymbol("Label9").readResolve();
    Lit114 = new FString("com.google.appinventor.components.runtime.Label");
    Lit113 = new FString("com.google.appinventor.components.runtime.HorizontalArrangement");
    Lit112 = (SimpleSymbol)new SimpleSymbol("HorizontalArrangement3").readResolve();
    Lit111 = new FString("com.google.appinventor.components.runtime.HorizontalArrangement");
    Lit110 = new FString("com.google.appinventor.components.runtime.Label");
    localObject = new int[2];
    localObject[0] = -1;
    Lit109 = IntNum.make((int[])localObject);
    Lit108 = (SimpleSymbol)new SimpleSymbol("Label8").readResolve();
    Lit107 = new FString("com.google.appinventor.components.runtime.Label");
    Lit106 = (SimpleSymbol)new SimpleSymbol("Click").readResolve();
    Lit105 = (SimpleSymbol)new SimpleSymbol("RememberButton$Click").readResolve();
    Lit104 = PairWithPosition.make(Lit5, PairWithPosition.make(Lit175, LList.Empty, "/tmp/1439383140418_0.797949561504734-0/youngandroidproject/../src/appinventor/ai_prafulmathur95/whereismycar/Screen1.yail", 664258), "/tmp/1439383140418_0.797949561504734-0/youngandroidproject/../src/appinventor/ai_prafulmathur95/whereismycar/Screen1.yail", 664252);
    Lit103 = PairWithPosition.make(Lit5, PairWithPosition.make(Lit175, LList.Empty, "/tmp/1439383140418_0.797949561504734-0/youngandroidproject/../src/appinventor/ai_prafulmathur95/whereismycar/Screen1.yail", 664130), "/tmp/1439383140418_0.797949561504734-0/youngandroidproject/../src/appinventor/ai_prafulmathur95/whereismycar/Screen1.yail", 664124);
    Lit102 = PairWithPosition.make(Lit5, PairWithPosition.make(Lit175, LList.Empty, "/tmp/1439383140418_0.797949561504734-0/youngandroidproject/../src/appinventor/ai_prafulmathur95/whereismycar/Screen1.yail", 664004), "/tmp/1439383140418_0.797949561504734-0/youngandroidproject/../src/appinventor/ai_prafulmathur95/whereismycar/Screen1.yail", 663998);
    Lit101 = (SimpleSymbol)new SimpleSymbol("StoreValue").readResolve();
    Lit100 = (SimpleSymbol)new SimpleSymbol("Longitude").readResolve();
    Lit99 = (SimpleSymbol)new SimpleSymbol("Latitude").readResolve();
    Lit98 = (SimpleSymbol)new SimpleSymbol("CurrentAddress").readResolve();
    Lit97 = new FString("com.google.appinventor.components.runtime.Button");
    Lit96 = (SimpleSymbol)new SimpleSymbol("Image").readResolve();
    Lit95 = IntNum.make(16777215);
    Lit94 = (SimpleSymbol)new SimpleSymbol("RememberButton").readResolve();
    Lit93 = new FString("com.google.appinventor.components.runtime.Button");
    Lit92 = new FString("com.google.appinventor.components.runtime.HorizontalArrangement");
    Lit91 = (SimpleSymbol)new SimpleSymbol("HorizontalArrangement6").readResolve();
    Lit90 = new FString("com.google.appinventor.components.runtime.HorizontalArrangement");
    Lit89 = new FString("com.google.appinventor.components.runtime.Label");
    localObject = new int[2];
    localObject[0] = -1;
    Lit88 = IntNum.make((int[])localObject);
    Lit87 = (SimpleSymbol)new SimpleSymbol("currentlongLabel").readResolve();
    Lit86 = new FString("com.google.appinventor.components.runtime.Label");
    Lit85 = new FString("com.google.appinventor.components.runtime.Label");
    localObject = new int[2];
    localObject[0] = -1;
    Lit84 = IntNum.make((int[])localObject);
    Lit83 = (SimpleSymbol)new SimpleSymbol("Label6").readResolve();
    Lit82 = new FString("com.google.appinventor.components.runtime.Label");
    Lit81 = new FString("com.google.appinventor.components.runtime.Label");
    localObject = new int[2];
    localObject[0] = -1;
    Lit80 = IntNum.make((int[])localObject);
    Lit79 = (SimpleSymbol)new SimpleSymbol("currentlatlabel").readResolve();
    Lit78 = new FString("com.google.appinventor.components.runtime.Label");
    Lit77 = new FString("com.google.appinventor.components.runtime.Label");
    localObject = new int[2];
    localObject[0] = -1;
    Lit76 = IntNum.make((int[])localObject);
    Lit75 = (SimpleSymbol)new SimpleSymbol("Label4").readResolve();
    Lit74 = new FString("com.google.appinventor.components.runtime.Label");
    Lit73 = new FString("com.google.appinventor.components.runtime.HorizontalArrangement");
    Lit72 = (SimpleSymbol)new SimpleSymbol("HorizontalArrangement2").readResolve();
    Lit71 = new FString("com.google.appinventor.components.runtime.HorizontalArrangement");
    Lit70 = new FString("com.google.appinventor.components.runtime.Label");
    localObject = new int[2];
    localObject[0] = -1;
    Lit69 = IntNum.make((int[])localObject);
    Lit68 = IntNum.make(18);
    Lit67 = (SimpleSymbol)new SimpleSymbol("currentaddressdatalabel").readResolve();
    Lit66 = new FString("com.google.appinventor.components.runtime.Label");
    Lit65 = new FString("com.google.appinventor.components.runtime.Label");
    localObject = new int[2];
    localObject[0] = -1;
    Lit64 = IntNum.make((int[])localObject);
    Lit63 = IntNum.make(20);
    Lit62 = (SimpleSymbol)new SimpleSymbol("Label2").readResolve();
    Lit61 = new FString("com.google.appinventor.components.runtime.Label");
    Lit60 = new FString("com.google.appinventor.components.runtime.HorizontalArrangement");
    Lit59 = (SimpleSymbol)new SimpleSymbol("HorizontalArrangement1").readResolve();
    Lit58 = new FString("com.google.appinventor.components.runtime.HorizontalArrangement");
    Lit57 = new FString("com.google.appinventor.components.runtime.Label");
    localObject = new int[2];
    localObject[0] = -1;
    Lit56 = IntNum.make((int[])localObject);
    Lit55 = (SimpleSymbol)new SimpleSymbol("TextColor").readResolve();
    Lit54 = IntNum.make(2);
    Lit53 = (SimpleSymbol)new SimpleSymbol("FontTypeface").readResolve();
    Lit52 = IntNum.make(25);
    Lit51 = (SimpleSymbol)new SimpleSymbol("FontSize").readResolve();
    Lit50 = (SimpleSymbol)new SimpleSymbol("Label1").readResolve();
    Lit49 = new FString("com.google.appinventor.components.runtime.Label");
    Lit48 = new FString("com.google.appinventor.components.runtime.Canvas");
    Lit47 = IntNum.make(50);
    Lit46 = (SimpleSymbol)new SimpleSymbol("Canvas1").readResolve();
    Lit45 = new FString("com.google.appinventor.components.runtime.Canvas");
    Lit44 = new FString("com.google.appinventor.components.runtime.HorizontalArrangement");
    Lit43 = (SimpleSymbol)new SimpleSymbol("HorizontalArrangement5").readResolve();
    Lit42 = new FString("com.google.appinventor.components.runtime.HorizontalArrangement");
    Lit41 = new FString("com.google.appinventor.components.runtime.Canvas");
    Lit40 = IntNum.make(-2);
    Lit39 = (SimpleSymbol)new SimpleSymbol("Width").readResolve();
    Lit38 = IntNum.make(70);
    Lit37 = (SimpleSymbol)new SimpleSymbol("Height").readResolve();
    Lit36 = (SimpleSymbol)new SimpleSymbol("Canvas2").readResolve();
    Lit35 = new FString("com.google.appinventor.components.runtime.Canvas");
    Lit34 = (SimpleSymbol)new SimpleSymbol("Initialize").readResolve();
    Lit33 = (SimpleSymbol)new SimpleSymbol("Screen1$Initialize").readResolve();
    Lit32 = (SimpleSymbol)new SimpleSymbol("directionbutton").readResolve();
    Lit31 = PairWithPosition.make(Lit5, PairWithPosition.make(Lit175, LList.Empty, "/tmp/1439383140418_0.797949561504734-0/youngandroidproject/../src/appinventor/ai_prafulmathur95/whereismycar/Screen1.yail", 90842), "/tmp/1439383140418_0.797949561504734-0/youngandroidproject/../src/appinventor/ai_prafulmathur95/whereismycar/Screen1.yail", 90836);
    Lit30 = (SimpleSymbol)new SimpleSymbol("TinyDB3").readResolve();
    Lit29 = (SimpleSymbol)new SimpleSymbol("rememberedLongLabel").readResolve();
    Lit28 = PairWithPosition.make(Lit5, PairWithPosition.make(Lit175, LList.Empty, "/tmp/1439383140418_0.797949561504734-0/youngandroidproject/../src/appinventor/ai_prafulmathur95/whereismycar/Screen1.yail", 90696), "/tmp/1439383140418_0.797949561504734-0/youngandroidproject/../src/appinventor/ai_prafulmathur95/whereismycar/Screen1.yail", 90690);
    Lit27 = (SimpleSymbol)new SimpleSymbol("TinyDB2").readResolve();
    Lit26 = (SimpleSymbol)new SimpleSymbol("rememberedlatLabel").readResolve();
    Lit25 = (SimpleSymbol)new SimpleSymbol("Text").readResolve();
    Lit24 = (SimpleSymbol)new SimpleSymbol("rememberedaddressdatalabel").readResolve();
    localObject = (SimpleSymbol)new SimpleSymbol("number").readResolve();
    Lit8 = (SimpleSymbol)localObject;
    Lit23 = PairWithPosition.make(localObject, PairWithPosition.make(Lit8, LList.Empty, "/tmp/1439383140418_0.797949561504734-0/youngandroidproject/../src/appinventor/ai_prafulmathur95/whereismycar/Screen1.yail", 90452), "/tmp/1439383140418_0.797949561504734-0/youngandroidproject/../src/appinventor/ai_prafulmathur95/whereismycar/Screen1.yail", 90444);
    Lit22 = IntNum.make(0);
    Lit21 = PairWithPosition.make(Lit5, LList.Empty, "/tmp/1439383140418_0.797949561504734-0/youngandroidproject/../src/appinventor/ai_prafulmathur95/whereismycar/Screen1.yail", 90423);
    Lit20 = PairWithPosition.make(Lit5, PairWithPosition.make(Lit175, LList.Empty, "/tmp/1439383140418_0.797949561504734-0/youngandroidproject/../src/appinventor/ai_prafulmathur95/whereismycar/Screen1.yail", 90289), "/tmp/1439383140418_0.797949561504734-0/youngandroidproject/../src/appinventor/ai_prafulmathur95/whereismycar/Screen1.yail", 90283);
    Lit19 = (SimpleSymbol)new SimpleSymbol("GetValue").readResolve();
    Lit18 = (SimpleSymbol)new SimpleSymbol("TinyDB1").readResolve();
    Lit17 = (SimpleSymbol)new SimpleSymbol("Enabled").readResolve();
    Lit16 = (SimpleSymbol)new SimpleSymbol("LocationSensor1").readResolve();
    Lit15 = (SimpleSymbol)new SimpleSymbol("Title").readResolve();
    Lit14 = (SimpleSymbol)new SimpleSymbol("boolean").readResolve();
    Lit13 = (SimpleSymbol)new SimpleSymbol("Scrollable").readResolve();
    Lit12 = (SimpleSymbol)new SimpleSymbol("OpenScreenAnimation").readResolve();
    Lit11 = (SimpleSymbol)new SimpleSymbol("Icon").readResolve();
    Lit10 = (SimpleSymbol)new SimpleSymbol("CloseScreenAnimation").readResolve();
    Lit9 = (SimpleSymbol)new SimpleSymbol("BackgroundImage").readResolve();
    localObject = new int[2];
    localObject[0] = -16777216;
    Lit7 = IntNum.make((int[])localObject);
    Lit6 = (SimpleSymbol)new SimpleSymbol("BackgroundColor").readResolve();
    Lit4 = (SimpleSymbol)new SimpleSymbol("AppName").readResolve();
    Lit3 = (SimpleSymbol)new SimpleSymbol("g$tempAddress").readResolve();
    Lit2 = (SimpleSymbol)new SimpleSymbol("*the-null-value*").readResolve();
    Lit1 = (SimpleSymbol)new SimpleSymbol("getMessage").readResolve();
  }
  
  public Screen1()
  {
    ModuleInfo.register(this);
    Screen1.frame localframe = new Screen1.frame();
    localframe.$main = this;
    this.android$Mnlog$Mnform = new ModuleMethod(localframe, 1, Lit163, 4097);
    this.add$Mnto$Mnform$Mnenvironment = new ModuleMethod(localframe, 2, Lit164, 8194);
    this.lookup$Mnin$Mnform$Mnenvironment = new ModuleMethod(localframe, 3, Lit165, 8193);
    this.is$Mnbound$Mnin$Mnform$Mnenvironment = new ModuleMethod(localframe, 5, Lit166, 4097);
    this.add$Mnto$Mnglobal$Mnvar$Mnenvironment = new ModuleMethod(localframe, 6, Lit167, 8194);
    this.add$Mnto$Mnevents = new ModuleMethod(localframe, 7, Lit168, 8194);
    this.add$Mnto$Mncomponents = new ModuleMethod(localframe, 8, Lit169, 16388);
    this.add$Mnto$Mnglobal$Mnvars = new ModuleMethod(localframe, 9, Lit170, 8194);
    this.add$Mnto$Mnform$Mndo$Mnafter$Mncreation = new ModuleMethod(localframe, 10, Lit171, 4097);
    this.send$Mnerror = new ModuleMethod(localframe, 11, Lit172, 4097);
    this.process$Mnexception = new ModuleMethod(localframe, 12, "process-exception", 4097);
    this.dispatchEvent = new ModuleMethod(localframe, 13, Lit173, 16388);
    this.lookup$Mnhandler = new ModuleMethod(localframe, 14, Lit174, 8194);
    ModuleMethod localModuleMethod = new ModuleMethod(localframe, 15, null, 0);
    localModuleMethod.setProperty("source-location", "/tmp/runtime8732862338101452200.scm:541");
    lambda$Fn1 = localModuleMethod;
    this.$define = new ModuleMethod(localframe, 16, "$define", 0);
    lambda$Fn2 = new ModuleMethod(localframe, 17, null, 0);
    lambda$Fn3 = new ModuleMethod(localframe, 18, null, 0);
    this.Screen1$Initialize = new ModuleMethod(localframe, 19, Lit33, 0);
    lambda$Fn4 = new ModuleMethod(localframe, 20, null, 0);
    lambda$Fn5 = new ModuleMethod(localframe, 21, null, 0);
    lambda$Fn6 = new ModuleMethod(localframe, 22, null, 0);
    lambda$Fn7 = new ModuleMethod(localframe, 23, null, 0);
    lambda$Fn8 = new ModuleMethod(localframe, 24, null, 0);
    lambda$Fn9 = new ModuleMethod(localframe, 25, null, 0);
    lambda$Fn10 = new ModuleMethod(localframe, 26, null, 0);
    lambda$Fn11 = new ModuleMethod(localframe, 27, null, 0);
    lambda$Fn12 = new ModuleMethod(localframe, 28, null, 0);
    lambda$Fn13 = new ModuleMethod(localframe, 29, null, 0);
    lambda$Fn14 = new ModuleMethod(localframe, 30, null, 0);
    lambda$Fn15 = new ModuleMethod(localframe, 31, null, 0);
    lambda$Fn16 = new ModuleMethod(localframe, 32, null, 0);
    lambda$Fn17 = new ModuleMethod(localframe, 33, null, 0);
    lambda$Fn18 = new ModuleMethod(localframe, 34, null, 0);
    lambda$Fn19 = new ModuleMethod(localframe, 35, null, 0);
    lambda$Fn20 = new ModuleMethod(localframe, 36, null, 0);
    lambda$Fn21 = new ModuleMethod(localframe, 37, null, 0);
    lambda$Fn22 = new ModuleMethod(localframe, 38, null, 0);
    lambda$Fn23 = new ModuleMethod(localframe, 39, null, 0);
    lambda$Fn24 = new ModuleMethod(localframe, 40, null, 0);
    lambda$Fn25 = new ModuleMethod(localframe, 41, null, 0);
    this.RememberButton$Click = new ModuleMethod(localframe, 42, Lit105, 0);
    lambda$Fn26 = new ModuleMethod(localframe, 43, null, 0);
    lambda$Fn27 = new ModuleMethod(localframe, 44, null, 0);
    lambda$Fn28 = new ModuleMethod(localframe, 45, null, 0);
    lambda$Fn29 = new ModuleMethod(localframe, 46, null, 0);
    lambda$Fn30 = new ModuleMethod(localframe, 47, null, 0);
    lambda$Fn31 = new ModuleMethod(localframe, 48, null, 0);
    lambda$Fn32 = new ModuleMethod(localframe, 49, null, 0);
    lambda$Fn33 = new ModuleMethod(localframe, 50, null, 0);
    lambda$Fn34 = new ModuleMethod(localframe, 51, null, 0);
    lambda$Fn35 = new ModuleMethod(localframe, 52, null, 0);
    lambda$Fn36 = new ModuleMethod(localframe, 53, null, 0);
    lambda$Fn37 = new ModuleMethod(localframe, 54, null, 0);
    lambda$Fn38 = new ModuleMethod(localframe, 55, null, 0);
    lambda$Fn39 = new ModuleMethod(localframe, 56, null, 0);
    lambda$Fn40 = new ModuleMethod(localframe, 57, null, 0);
    lambda$Fn41 = new ModuleMethod(localframe, 58, null, 0);
    lambda$Fn42 = new ModuleMethod(localframe, 59, null, 0);
    lambda$Fn43 = new ModuleMethod(localframe, 60, null, 0);
    this.directionbutton$Click = new ModuleMethod(localframe, 61, Lit147, 0);
    this.LocationSensor1$LocationChanged = new ModuleMethod(localframe, 62, Lit150, 12291);
    lambda$Fn44 = new ModuleMethod(localframe, 63, null, 0);
    lambda$Fn45 = new ModuleMethod(localframe, 64, null, 0);
  }
  
  static Object lambda10()
  {
    runtime.setAndCoerceProperty$Ex(Lit46, Lit9, "geolocate.png", Lit5);
    runtime.setAndCoerceProperty$Ex(Lit46, Lit37, Lit47, Lit8);
    return runtime.setAndCoerceProperty$Ex(Lit46, Lit39, Lit47, Lit8);
  }
  
  static Object lambda11()
  {
    runtime.setAndCoerceProperty$Ex(Lit50, Lit51, Lit52, Lit8);
    runtime.setAndCoerceProperty$Ex(Lit50, Lit53, Lit54, Lit8);
    runtime.setAndCoerceProperty$Ex(Lit50, Lit39, Lit40, Lit8);
    runtime.setAndCoerceProperty$Ex(Lit50, Lit25, "Your current location", Lit5);
    return runtime.setAndCoerceProperty$Ex(Lit50, Lit55, Lit56, Lit8);
  }
  
  static Object lambda12()
  {
    runtime.setAndCoerceProperty$Ex(Lit50, Lit51, Lit52, Lit8);
    runtime.setAndCoerceProperty$Ex(Lit50, Lit53, Lit54, Lit8);
    runtime.setAndCoerceProperty$Ex(Lit50, Lit39, Lit40, Lit8);
    runtime.setAndCoerceProperty$Ex(Lit50, Lit25, "Your current location", Lit5);
    return runtime.setAndCoerceProperty$Ex(Lit50, Lit55, Lit56, Lit8);
  }
  
  static Object lambda13()
  {
    runtime.setAndCoerceProperty$Ex(Lit62, Lit51, Lit63, Lit8);
    runtime.setAndCoerceProperty$Ex(Lit62, Lit53, Lit54, Lit8);
    runtime.setAndCoerceProperty$Ex(Lit62, Lit25, "Address:", Lit5);
    return runtime.setAndCoerceProperty$Ex(Lit62, Lit55, Lit64, Lit8);
  }
  
  static Object lambda14()
  {
    runtime.setAndCoerceProperty$Ex(Lit62, Lit51, Lit63, Lit8);
    runtime.setAndCoerceProperty$Ex(Lit62, Lit53, Lit54, Lit8);
    runtime.setAndCoerceProperty$Ex(Lit62, Lit25, "Address:", Lit5);
    return runtime.setAndCoerceProperty$Ex(Lit62, Lit55, Lit64, Lit8);
  }
  
  static Object lambda15()
  {
    runtime.setAndCoerceProperty$Ex(Lit67, Lit51, Lit68, Lit8);
    runtime.setAndCoerceProperty$Ex(Lit67, Lit25, "unknown", Lit5);
    return runtime.setAndCoerceProperty$Ex(Lit67, Lit55, Lit69, Lit8);
  }
  
  static Object lambda16()
  {
    runtime.setAndCoerceProperty$Ex(Lit67, Lit51, Lit68, Lit8);
    runtime.setAndCoerceProperty$Ex(Lit67, Lit25, "unknown", Lit5);
    return runtime.setAndCoerceProperty$Ex(Lit67, Lit55, Lit69, Lit8);
  }
  
  static Object lambda17()
  {
    runtime.setAndCoerceProperty$Ex(Lit75, Lit51, Lit63, Lit8);
    runtime.setAndCoerceProperty$Ex(Lit75, Lit53, Lit54, Lit8);
    runtime.setAndCoerceProperty$Ex(Lit75, Lit25, "GPS :", Lit5);
    return runtime.setAndCoerceProperty$Ex(Lit75, Lit55, Lit76, Lit8);
  }
  
  static Object lambda18()
  {
    runtime.setAndCoerceProperty$Ex(Lit75, Lit51, Lit63, Lit8);
    runtime.setAndCoerceProperty$Ex(Lit75, Lit53, Lit54, Lit8);
    runtime.setAndCoerceProperty$Ex(Lit75, Lit25, "GPS :", Lit5);
    return runtime.setAndCoerceProperty$Ex(Lit75, Lit55, Lit76, Lit8);
  }
  
  static Object lambda19()
  {
    runtime.setAndCoerceProperty$Ex(Lit79, Lit25, "0", Lit5);
    return runtime.setAndCoerceProperty$Ex(Lit79, Lit55, Lit80, Lit8);
  }
  
  /* Error */
  public static SimpleSymbol lambda1symbolAppend$V(Object[] paramArrayOfObject)
  {
    // Byte code:
    //   0: aload_0
    //   1: iconst_0
    //   2: invokestatic 1059	gnu/lists/LList:makeList	([Ljava/lang/Object;I)Lgnu/lists/LList;
    //   5: astore_1
    //   6: getstatic 1065	kawa/standard/Scheme:apply	Lgnu/kawa/functions/Apply;
    //   9: astore_2
    //   10: getstatic 1070	kawa/lib/strings:string$Mnappend	Lgnu/expr/ModuleMethod;
    //   13: astore_3
    //   14: getstatic 423	gnu/lists/LList:Empty	Lgnu/lists/LList;
    //   17: astore_0
    //   18: aload_1
    //   19: getstatic 423	gnu/lists/LList:Empty	Lgnu/lists/LList;
    //   22: if_acmpne +23 -> 45
    //   25: aload_2
    //   26: aload_3
    //   27: aload_0
    //   28: invokestatic 1074	gnu/lists/LList:reverseInPlace	(Ljava/lang/Object;)Lgnu/lists/LList;
    //   31: invokevirtual 1080	gnu/mapping/Procedure:apply2	(Ljava/lang/Object;Ljava/lang/Object;)Ljava/lang/Object;
    //   34: astore_0
    //   35: aload_0
    //   36: checkcast 1082	java/lang/CharSequence
    //   39: astore_1
    //   40: aload_1
    //   41: invokestatic 1088	kawa/lib/misc:string$To$Symbol	(Ljava/lang/CharSequence;)Lgnu/mapping/SimpleSymbol;
    //   44: areturn
    //   45: aload_1
    //   46: checkcast 1090	gnu/lists/Pair
    //   49: astore 4
    //   51: aload 4
    //   53: invokevirtual 1093	gnu/lists/Pair:getCdr	()Ljava/lang/Object;
    //   56: astore_1
    //   57: aload 4
    //   59: invokevirtual 1096	gnu/lists/Pair:getCar	()Ljava/lang/Object;
    //   62: astore 4
    //   64: aload 4
    //   66: checkcast 1098	gnu/mapping/Symbol
    //   69: astore 5
    //   71: aload 5
    //   73: invokestatic 1102	kawa/lib/misc:symbol$To$String	(Lgnu/mapping/Symbol;)Ljava/lang/String;
    //   76: aload_0
    //   77: invokestatic 1105	gnu/lists/Pair:make	(Ljava/lang/Object;Ljava/lang/Object;)Lgnu/lists/Pair;
    //   80: astore_0
    //   81: goto -63 -> 18
    //   84: astore_0
    //   85: new 1107	gnu/mapping/WrongType
    //   88: dup
    //   89: aload_0
    //   90: ldc_w 1109
    //   93: bipush -2
    //   95: aload_1
    //   96: invokespecial 1112	gnu/mapping/WrongType:<init>	(Ljava/lang/ClassCastException;Ljava/lang/String;ILjava/lang/Object;)V
    //   99: athrow
    //   100: astore_0
    //   101: new 1107	gnu/mapping/WrongType
    //   104: dup
    //   105: aload_0
    //   106: ldc_w 1114
    //   109: iconst_1
    //   110: aload 4
    //   112: invokespecial 1112	gnu/mapping/WrongType:<init>	(Ljava/lang/ClassCastException;Ljava/lang/String;ILjava/lang/Object;)V
    //   115: athrow
    //   116: astore_1
    //   117: new 1107	gnu/mapping/WrongType
    //   120: dup
    //   121: aload_1
    //   122: ldc_w 1116
    //   125: iconst_1
    //   126: aload_0
    //   127: invokespecial 1112	gnu/mapping/WrongType:<init>	(Ljava/lang/ClassCastException;Ljava/lang/String;ILjava/lang/Object;)V
    //   130: athrow
    // Local variable table:
    //   start	length	slot	name	signature
    //   0	131	0	paramArrayOfObject	Object[]
    //   5	91	1	localObject1	Object
    //   116	6	1	localClassCastException	ClassCastException
    //   9	17	2	localApply	gnu.kawa.functions.Apply
    //   13	14	3	localModuleMethod	ModuleMethod
    //   49	62	4	localObject2	Object
    //   69	3	5	localSymbol	Symbol
    // Exception table:
    //   from	to	target	type
    //   45	51	84	java/lang/ClassCastException
    //   64	71	100	java/lang/ClassCastException
    //   35	40	116	java/lang/ClassCastException
  }
  
  static Object lambda2()
  {
    return null;
  }
  
  static Object lambda20()
  {
    runtime.setAndCoerceProperty$Ex(Lit79, Lit25, "0", Lit5);
    return runtime.setAndCoerceProperty$Ex(Lit79, Lit55, Lit80, Lit8);
  }
  
  static Object lambda21()
  {
    runtime.setAndCoerceProperty$Ex(Lit83, Lit25, ",", Lit5);
    return runtime.setAndCoerceProperty$Ex(Lit83, Lit55, Lit84, Lit8);
  }
  
  static Object lambda22()
  {
    runtime.setAndCoerceProperty$Ex(Lit83, Lit25, ",", Lit5);
    return runtime.setAndCoerceProperty$Ex(Lit83, Lit55, Lit84, Lit8);
  }
  
  static Object lambda23()
  {
    runtime.setAndCoerceProperty$Ex(Lit87, Lit25, "0", Lit5);
    return runtime.setAndCoerceProperty$Ex(Lit87, Lit55, Lit88, Lit8);
  }
  
  static Object lambda24()
  {
    runtime.setAndCoerceProperty$Ex(Lit87, Lit25, "0", Lit5);
    return runtime.setAndCoerceProperty$Ex(Lit87, Lit55, Lit88, Lit8);
  }
  
  static Object lambda25()
  {
    runtime.setAndCoerceProperty$Ex(Lit94, Lit6, Lit95, Lit8);
    runtime.setAndCoerceProperty$Ex(Lit94, Lit37, Lit47, Lit8);
    runtime.setAndCoerceProperty$Ex(Lit94, Lit39, Lit40, Lit8);
    runtime.setAndCoerceProperty$Ex(Lit94, Lit96, "download(1).jpeg", Lit5);
    return runtime.setAndCoerceProperty$Ex(Lit94, Lit25, "Park Here", Lit5);
  }
  
  static Object lambda26()
  {
    runtime.setAndCoerceProperty$Ex(Lit94, Lit6, Lit95, Lit8);
    runtime.setAndCoerceProperty$Ex(Lit94, Lit37, Lit47, Lit8);
    runtime.setAndCoerceProperty$Ex(Lit94, Lit39, Lit40, Lit8);
    runtime.setAndCoerceProperty$Ex(Lit94, Lit96, "download(1).jpeg", Lit5);
    return runtime.setAndCoerceProperty$Ex(Lit94, Lit25, "Park Here", Lit5);
  }
  
  static Object lambda27()
  {
    runtime.setAndCoerceProperty$Ex(Lit108, Lit51, Lit52, Lit8);
    runtime.setAndCoerceProperty$Ex(Lit108, Lit53, Lit54, Lit8);
    runtime.setAndCoerceProperty$Ex(Lit108, Lit25, "Initial Location", Lit5);
    return runtime.setAndCoerceProperty$Ex(Lit108, Lit55, Lit109, Lit8);
  }
  
  static Object lambda28()
  {
    runtime.setAndCoerceProperty$Ex(Lit108, Lit51, Lit52, Lit8);
    runtime.setAndCoerceProperty$Ex(Lit108, Lit53, Lit54, Lit8);
    runtime.setAndCoerceProperty$Ex(Lit108, Lit25, "Initial Location", Lit5);
    return runtime.setAndCoerceProperty$Ex(Lit108, Lit55, Lit109, Lit8);
  }
  
  static Object lambda29()
  {
    runtime.setAndCoerceProperty$Ex(Lit115, Lit51, Lit63, Lit8);
    runtime.setAndCoerceProperty$Ex(Lit115, Lit53, Lit54, Lit8);
    runtime.setAndCoerceProperty$Ex(Lit115, Lit25, "Address :", Lit5);
    return runtime.setAndCoerceProperty$Ex(Lit115, Lit55, Lit116, Lit8);
  }
  
  static String lambda3()
  {
    return "";
  }
  
  static Object lambda30()
  {
    runtime.setAndCoerceProperty$Ex(Lit115, Lit51, Lit63, Lit8);
    runtime.setAndCoerceProperty$Ex(Lit115, Lit53, Lit54, Lit8);
    runtime.setAndCoerceProperty$Ex(Lit115, Lit25, "Address :", Lit5);
    return runtime.setAndCoerceProperty$Ex(Lit115, Lit55, Lit116, Lit8);
  }
  
  static Object lambda31()
  {
    runtime.setAndCoerceProperty$Ex(Lit24, Lit51, Lit68, Lit8);
    runtime.setAndCoerceProperty$Ex(Lit24, Lit25, "unknown", Lit5);
    return runtime.setAndCoerceProperty$Ex(Lit24, Lit55, Lit119, Lit8);
  }
  
  static Object lambda32()
  {
    runtime.setAndCoerceProperty$Ex(Lit24, Lit51, Lit68, Lit8);
    runtime.setAndCoerceProperty$Ex(Lit24, Lit25, "unknown", Lit5);
    return runtime.setAndCoerceProperty$Ex(Lit24, Lit55, Lit119, Lit8);
  }
  
  static Object lambda33()
  {
    runtime.setAndCoerceProperty$Ex(Lit125, Lit51, Lit63, Lit8);
    runtime.setAndCoerceProperty$Ex(Lit125, Lit53, Lit54, Lit8);
    runtime.setAndCoerceProperty$Ex(Lit125, Lit25, "GPS :", Lit5);
    return runtime.setAndCoerceProperty$Ex(Lit125, Lit55, Lit126, Lit8);
  }
  
  static Object lambda34()
  {
    runtime.setAndCoerceProperty$Ex(Lit125, Lit51, Lit63, Lit8);
    runtime.setAndCoerceProperty$Ex(Lit125, Lit53, Lit54, Lit8);
    runtime.setAndCoerceProperty$Ex(Lit125, Lit25, "GPS :", Lit5);
    return runtime.setAndCoerceProperty$Ex(Lit125, Lit55, Lit126, Lit8);
  }
  
  static Object lambda35()
  {
    runtime.setAndCoerceProperty$Ex(Lit26, Lit25, "0", Lit5);
    return runtime.setAndCoerceProperty$Ex(Lit26, Lit55, Lit129, Lit8);
  }
  
  static Object lambda36()
  {
    runtime.setAndCoerceProperty$Ex(Lit26, Lit25, "0", Lit5);
    return runtime.setAndCoerceProperty$Ex(Lit26, Lit55, Lit129, Lit8);
  }
  
  static Object lambda37()
  {
    runtime.setAndCoerceProperty$Ex(Lit132, Lit25, ",", Lit5);
    return runtime.setAndCoerceProperty$Ex(Lit132, Lit55, Lit133, Lit8);
  }
  
  static Object lambda38()
  {
    runtime.setAndCoerceProperty$Ex(Lit132, Lit25, ",", Lit5);
    return runtime.setAndCoerceProperty$Ex(Lit132, Lit55, Lit133, Lit8);
  }
  
  static Object lambda39()
  {
    runtime.setAndCoerceProperty$Ex(Lit29, Lit25, "0", Lit5);
    return runtime.setAndCoerceProperty$Ex(Lit29, Lit55, Lit136, Lit8);
  }
  
  static Object lambda4()
  {
    runtime.setAndCoerceProperty$Ex(Lit0, Lit4, "whereismycar", Lit5);
    runtime.setAndCoerceProperty$Ex(Lit0, Lit6, Lit7, Lit8);
    runtime.setAndCoerceProperty$Ex(Lit0, Lit9, "images(2).jpeg", Lit5);
    runtime.setAndCoerceProperty$Ex(Lit0, Lit10, "fade", Lit5);
    runtime.setAndCoerceProperty$Ex(Lit0, Lit11, "images.jpeg", Lit5);
    runtime.setAndCoerceProperty$Ex(Lit0, Lit12, "zoom", Lit5);
    runtime.setAndCoerceProperty$Ex(Lit0, Lit13, Boolean.TRUE, Lit14);
    return runtime.setAndCoerceProperty$Ex(Lit0, Lit15, "Where's  My  Car", Lit5);
  }
  
  static Object lambda40()
  {
    runtime.setAndCoerceProperty$Ex(Lit29, Lit25, "0", Lit5);
    return runtime.setAndCoerceProperty$Ex(Lit29, Lit55, Lit136, Lit8);
  }
  
  static Object lambda41()
  {
    runtime.setAndCoerceProperty$Ex(Lit32, Lit37, Lit47, Lit8);
    runtime.setAndCoerceProperty$Ex(Lit32, Lit39, Lit40, Lit8);
    runtime.setAndCoerceProperty$Ex(Lit32, Lit96, "download(1).jpeg", Lit5);
    return runtime.setAndCoerceProperty$Ex(Lit32, Lit25, "Show Directions To Initial Location", Lit5);
  }
  
  static Object lambda42()
  {
    runtime.setAndCoerceProperty$Ex(Lit32, Lit37, Lit47, Lit8);
    runtime.setAndCoerceProperty$Ex(Lit32, Lit39, Lit40, Lit8);
    runtime.setAndCoerceProperty$Ex(Lit32, Lit96, "download(1).jpeg", Lit5);
    return runtime.setAndCoerceProperty$Ex(Lit32, Lit25, "Show Directions To Initial Location", Lit5);
  }
  
  static Object lambda43()
  {
    return runtime.callYailPrimitive(runtime.yail$Mnequal$Qu, LList.list2(runtime.getProperty$1(Lit79, Lit25), runtime.getProperty$1(Lit26, Lit25)), Lit140, "=");
  }
  
  static Object lambda44()
  {
    return runtime.callYailPrimitive(runtime.yail$Mnequal$Qu, LList.list2(runtime.getProperty$1(Lit87, Lit25), runtime.getProperty$1(Lit29, Lit25)), Lit141, "=");
  }
  
  static Object lambda45()
  {
    runtime.setAndCoerceProperty$Ex(Lit142, Lit153, "android.intent.action.VIEW", Lit5);
    runtime.setAndCoerceProperty$Ex(Lit142, Lit154, "com.google.android.maps.MapsActivity", Lit5);
    return runtime.setAndCoerceProperty$Ex(Lit142, Lit155, "com.google.android.apps.maps", Lit5);
  }
  
  static Object lambda46()
  {
    runtime.setAndCoerceProperty$Ex(Lit142, Lit153, "android.intent.action.VIEW", Lit5);
    runtime.setAndCoerceProperty$Ex(Lit142, Lit154, "com.google.android.maps.MapsActivity", Lit5);
    return runtime.setAndCoerceProperty$Ex(Lit142, Lit155, "com.google.android.apps.maps", Lit5);
  }
  
  static Object lambda5()
  {
    runtime.setAndCoerceProperty$Ex(Lit36, Lit9, "shanghai_city_skyline.png", Lit5);
    runtime.setAndCoerceProperty$Ex(Lit36, Lit37, Lit38, Lit8);
    return runtime.setAndCoerceProperty$Ex(Lit36, Lit39, Lit40, Lit8);
  }
  
  static Object lambda6()
  {
    runtime.setAndCoerceProperty$Ex(Lit36, Lit9, "shanghai_city_skyline.png", Lit5);
    runtime.setAndCoerceProperty$Ex(Lit36, Lit37, Lit38, Lit8);
    return runtime.setAndCoerceProperty$Ex(Lit36, Lit39, Lit40, Lit8);
  }
  
  static Object lambda7()
  {
    return runtime.setAndCoerceProperty$Ex(Lit43, Lit39, Lit40, Lit8);
  }
  
  static Object lambda8()
  {
    return runtime.setAndCoerceProperty$Ex(Lit43, Lit39, Lit40, Lit8);
  }
  
  static Object lambda9()
  {
    runtime.setAndCoerceProperty$Ex(Lit46, Lit9, "geolocate.png", Lit5);
    runtime.setAndCoerceProperty$Ex(Lit46, Lit37, Lit47, Lit8);
    return runtime.setAndCoerceProperty$Ex(Lit46, Lit39, Lit47, Lit8);
  }
  
  /* Error */
  public void $define()
  {
    // Byte code:
    //   0: invokestatic 1213	kawa/standard/Scheme:getInstance	()Lkawa/standard/Scheme;
    //   3: invokestatic 1219	gnu/expr/Language:setDefaults	(Lgnu/expr/Language;)V
    //   6: aload_0
    //   7: invokevirtual 1222	appinventor/ai_prafulmathur95/whereismycar/Screen1:run	()V
    //   10: aload_0
    //   11: putstatic 1224	appinventor/ai_prafulmathur95/whereismycar/Screen1:Screen1	Lappinventor/ai_prafulmathur95/whereismycar/Screen1;
    //   14: aload_0
    //   15: getstatic 864	appinventor/ai_prafulmathur95/whereismycar/Screen1:Lit0	Lgnu/mapping/SimpleSymbol;
    //   18: aload_0
    //   19: invokevirtual 1228	appinventor/ai_prafulmathur95/whereismycar/Screen1:addToFormEnvironment	(Lgnu/mapping/Symbol;Ljava/lang/Object;)V
    //   22: aload_0
    //   23: getfield 1230	appinventor/ai_prafulmathur95/whereismycar/Screen1:events$Mnto$Mnregister	Lgnu/lists/LList;
    //   26: astore_1
    //   27: aload_1
    //   28: getstatic 423	gnu/lists/LList:Empty	Lgnu/lists/LList;
    //   31: if_acmpne +96 -> 127
    //   34: aload_0
    //   35: getstatic 857	appinventor/ai_prafulmathur95/whereismycar/Screen1:Lit2	Lgnu/mapping/SimpleSymbol;
    //   38: getstatic 924	appinventor/ai_prafulmathur95/whereismycar/Screen1:lambda$Fn1	Lgnu/expr/ModuleMethod;
    //   41: invokevirtual 1233	appinventor/ai_prafulmathur95/whereismycar/Screen1:addToGlobalVars	(Ljava/lang/Object;Ljava/lang/Object;)V
    //   44: aload_0
    //   45: getfield 1235	appinventor/ai_prafulmathur95/whereismycar/Screen1:global$Mnvars$Mnto$Mncreate	Lgnu/lists/LList;
    //   48: invokestatic 1241	kawa/lib/lists:reverse	(Lgnu/lists/LList;)Lgnu/lists/LList;
    //   51: astore_1
    //   52: aload_1
    //   53: getstatic 423	gnu/lists/LList:Empty	Lgnu/lists/LList;
    //   56: if_acmpne +139 -> 195
    //   59: aload_0
    //   60: getfield 1243	appinventor/ai_prafulmathur95/whereismycar/Screen1:form$Mndo$Mnafter$Mncreation	Lgnu/lists/LList;
    //   63: invokestatic 1241	kawa/lib/lists:reverse	(Lgnu/lists/LList;)Lgnu/lists/LList;
    //   66: astore_1
    //   67: aload_1
    //   68: getstatic 423	gnu/lists/LList:Empty	Lgnu/lists/LList;
    //   71: if_acmpne +215 -> 286
    //   74: aload_0
    //   75: getfield 1245	appinventor/ai_prafulmathur95/whereismycar/Screen1:components$Mnto$Mncreate	Lgnu/lists/LList;
    //   78: invokestatic 1241	kawa/lib/lists:reverse	(Lgnu/lists/LList;)Lgnu/lists/LList;
    //   81: astore_1
    //   82: aload_1
    //   83: astore_2
    //   84: aload_2
    //   85: getstatic 423	gnu/lists/LList:Empty	Lgnu/lists/LList;
    //   88: if_acmpne +235 -> 323
    //   91: aload_1
    //   92: astore_2
    //   93: aload_2
    //   94: getstatic 423	gnu/lists/LList:Empty	Lgnu/lists/LList;
    //   97: if_acmpne +382 -> 479
    //   100: getstatic 423	gnu/lists/LList:Empty	Lgnu/lists/LList;
    //   103: astore_2
    //   104: aload_1
    //   105: aload_2
    //   106: if_acmpne +438 -> 544
    //   109: return
    //   110: astore_1
    //   111: aload_0
    //   112: aload_1
    //   113: invokevirtual 1247	java/lang/Exception:getMessage	()Ljava/lang/String;
    //   116: invokevirtual 1250	appinventor/ai_prafulmathur95/whereismycar/Screen1:androidLogForm	(Ljava/lang/Object;)V
    //   119: aload_0
    //   120: aload_1
    //   121: invokevirtual 1253	appinventor/ai_prafulmathur95/whereismycar/Screen1:processException	(Ljava/lang/Object;)V
    //   124: goto -114 -> 10
    //   127: aload_1
    //   128: checkcast 1090	gnu/lists/Pair
    //   131: astore_3
    //   132: aload_3
    //   133: invokevirtual 1096	gnu/lists/Pair:getCar	()Ljava/lang/Object;
    //   136: astore_2
    //   137: getstatic 1257	kawa/lib/lists:car	Lgnu/expr/GenericProc;
    //   140: aload_2
    //   141: invokevirtual 1261	gnu/mapping/Procedure:apply1	(Ljava/lang/Object;)Ljava/lang/Object;
    //   144: astore_1
    //   145: aload_1
    //   146: ifnonnull +33 -> 179
    //   149: aconst_null
    //   150: astore_1
    //   151: getstatic 1264	kawa/lib/lists:cdr	Lgnu/expr/GenericProc;
    //   154: aload_2
    //   155: invokevirtual 1261	gnu/mapping/Procedure:apply1	(Ljava/lang/Object;)Ljava/lang/Object;
    //   158: astore_2
    //   159: aload_2
    //   160: ifnonnull +27 -> 187
    //   163: aconst_null
    //   164: astore_2
    //   165: aload_0
    //   166: aload_1
    //   167: aload_2
    //   168: invokestatic 1270	com/google/appinventor/components/runtime/EventDispatcher:registerEventForDelegation	(Lcom/google/appinventor/components/runtime/HandlesEventDispatching;Ljava/lang/String;Ljava/lang/String;)V
    //   171: aload_3
    //   172: invokevirtual 1093	gnu/lists/Pair:getCdr	()Ljava/lang/Object;
    //   175: astore_1
    //   176: goto -149 -> 27
    //   179: aload_1
    //   180: invokevirtual 1275	java/lang/Object:toString	()Ljava/lang/String;
    //   183: astore_1
    //   184: goto -33 -> 151
    //   187: aload_2
    //   188: invokevirtual 1275	java/lang/Object:toString	()Ljava/lang/String;
    //   191: astore_2
    //   192: goto -27 -> 165
    //   195: aload_1
    //   196: checkcast 1090	gnu/lists/Pair
    //   199: astore_2
    //   200: aload_2
    //   201: invokevirtual 1096	gnu/lists/Pair:getCar	()Ljava/lang/Object;
    //   204: astore_3
    //   205: getstatic 1257	kawa/lib/lists:car	Lgnu/expr/GenericProc;
    //   208: aload_3
    //   209: invokevirtual 1261	gnu/mapping/Procedure:apply1	(Ljava/lang/Object;)Ljava/lang/Object;
    //   212: astore_1
    //   213: getstatic 1278	kawa/lib/lists:cadr	Lgnu/expr/GenericProc;
    //   216: aload_3
    //   217: invokevirtual 1261	gnu/mapping/Procedure:apply1	(Ljava/lang/Object;)Ljava/lang/Object;
    //   220: astore_3
    //   221: aload_1
    //   222: checkcast 1098	gnu/mapping/Symbol
    //   225: astore 4
    //   227: aload_0
    //   228: aload 4
    //   230: getstatic 1282	kawa/standard/Scheme:applyToArgs	Lgnu/kawa/functions/ApplyToArgs;
    //   233: aload_3
    //   234: invokevirtual 1261	gnu/mapping/Procedure:apply1	(Ljava/lang/Object;)Ljava/lang/Object;
    //   237: invokevirtual 1285	appinventor/ai_prafulmathur95/whereismycar/Screen1:addToGlobalVarEnvironment	(Lgnu/mapping/Symbol;Ljava/lang/Object;)V
    //   240: aload_2
    //   241: invokevirtual 1093	gnu/lists/Pair:getCdr	()Ljava/lang/Object;
    //   244: astore_1
    //   245: goto -193 -> 52
    //   248: astore_2
    //   249: new 1107	gnu/mapping/WrongType
    //   252: dup
    //   253: aload_2
    //   254: ldc_w 1109
    //   257: bipush -2
    //   259: aload_1
    //   260: invokespecial 1112	gnu/mapping/WrongType:<init>	(Ljava/lang/ClassCastException;Ljava/lang/String;ILjava/lang/Object;)V
    //   263: athrow
    //   264: astore_1
    //   265: aload_0
    //   266: aload_1
    //   267: invokevirtual 1253	appinventor/ai_prafulmathur95/whereismycar/Screen1:processException	(Ljava/lang/Object;)V
    //   270: return
    //   271: astore_2
    //   272: new 1107	gnu/mapping/WrongType
    //   275: dup
    //   276: aload_2
    //   277: ldc_w 345
    //   280: iconst_0
    //   281: aload_1
    //   282: invokespecial 1112	gnu/mapping/WrongType:<init>	(Ljava/lang/ClassCastException;Ljava/lang/String;ILjava/lang/Object;)V
    //   285: athrow
    //   286: aload_1
    //   287: checkcast 1090	gnu/lists/Pair
    //   290: astore_2
    //   291: aload_2
    //   292: invokevirtual 1096	gnu/lists/Pair:getCar	()Ljava/lang/Object;
    //   295: invokestatic 1288	kawa/lib/misc:force	(Ljava/lang/Object;)Ljava/lang/Object;
    //   298: pop
    //   299: aload_2
    //   300: invokevirtual 1093	gnu/lists/Pair:getCdr	()Ljava/lang/Object;
    //   303: astore_1
    //   304: goto -237 -> 67
    //   307: astore_2
    //   308: new 1107	gnu/mapping/WrongType
    //   311: dup
    //   312: aload_2
    //   313: ldc_w 1109
    //   316: bipush -2
    //   318: aload_1
    //   319: invokespecial 1112	gnu/mapping/WrongType:<init>	(Ljava/lang/ClassCastException;Ljava/lang/String;ILjava/lang/Object;)V
    //   322: athrow
    //   323: aload_2
    //   324: checkcast 1090	gnu/lists/Pair
    //   327: astore_3
    //   328: aload_3
    //   329: invokevirtual 1096	gnu/lists/Pair:getCar	()Ljava/lang/Object;
    //   332: astore 5
    //   334: getstatic 1291	kawa/lib/lists:caddr	Lgnu/expr/GenericProc;
    //   337: aload 5
    //   339: invokevirtual 1261	gnu/mapping/Procedure:apply1	(Ljava/lang/Object;)Ljava/lang/Object;
    //   342: astore_2
    //   343: getstatic 1294	kawa/lib/lists:cadddr	Lgnu/expr/GenericProc;
    //   346: aload 5
    //   348: invokevirtual 1261	gnu/mapping/Procedure:apply1	(Ljava/lang/Object;)Ljava/lang/Object;
    //   351: pop
    //   352: getstatic 1278	kawa/lib/lists:cadr	Lgnu/expr/GenericProc;
    //   355: aload 5
    //   357: invokevirtual 1261	gnu/mapping/Procedure:apply1	(Ljava/lang/Object;)Ljava/lang/Object;
    //   360: astore 4
    //   362: getstatic 1257	kawa/lib/lists:car	Lgnu/expr/GenericProc;
    //   365: aload 5
    //   367: invokevirtual 1261	gnu/mapping/Procedure:apply1	(Ljava/lang/Object;)Ljava/lang/Object;
    //   370: astore 5
    //   372: aload 5
    //   374: checkcast 1098	gnu/mapping/Symbol
    //   377: astore 6
    //   379: aload_0
    //   380: aload 6
    //   382: invokevirtual 1298	appinventor/ai_prafulmathur95/whereismycar/Screen1:lookupInFormEnvironment	(Lgnu/mapping/Symbol;)Ljava/lang/Object;
    //   385: astore 5
    //   387: getstatic 1303	gnu/kawa/reflect/Invoke:make	Lgnu/kawa/reflect/Invoke;
    //   390: aload 4
    //   392: aload 5
    //   394: invokevirtual 1080	gnu/mapping/Procedure:apply2	(Ljava/lang/Object;Ljava/lang/Object;)Ljava/lang/Object;
    //   397: astore 4
    //   399: getstatic 1309	gnu/kawa/reflect/SlotSet:set$Mnfield$Ex	Lgnu/kawa/reflect/SlotSet;
    //   402: aload_0
    //   403: aload_2
    //   404: aload 4
    //   406: invokevirtual 1313	gnu/mapping/Procedure:apply3	(Ljava/lang/Object;Ljava/lang/Object;Ljava/lang/Object;)Ljava/lang/Object;
    //   409: pop
    //   410: aload_2
    //   411: checkcast 1098	gnu/mapping/Symbol
    //   414: astore 5
    //   416: aload_0
    //   417: aload 5
    //   419: aload 4
    //   421: invokevirtual 1228	appinventor/ai_prafulmathur95/whereismycar/Screen1:addToFormEnvironment	(Lgnu/mapping/Symbol;Ljava/lang/Object;)V
    //   424: aload_3
    //   425: invokevirtual 1093	gnu/lists/Pair:getCdr	()Ljava/lang/Object;
    //   428: astore_2
    //   429: goto -345 -> 84
    //   432: astore_1
    //   433: new 1107	gnu/mapping/WrongType
    //   436: dup
    //   437: aload_1
    //   438: ldc_w 1109
    //   441: bipush -2
    //   443: aload_2
    //   444: invokespecial 1112	gnu/mapping/WrongType:<init>	(Ljava/lang/ClassCastException;Ljava/lang/String;ILjava/lang/Object;)V
    //   447: athrow
    //   448: astore_1
    //   449: new 1107	gnu/mapping/WrongType
    //   452: dup
    //   453: aload_1
    //   454: ldc_w 353
    //   457: iconst_0
    //   458: aload 5
    //   460: invokespecial 1112	gnu/mapping/WrongType:<init>	(Ljava/lang/ClassCastException;Ljava/lang/String;ILjava/lang/Object;)V
    //   463: athrow
    //   464: astore_1
    //   465: new 1107	gnu/mapping/WrongType
    //   468: dup
    //   469: aload_1
    //   470: ldc_w 357
    //   473: iconst_0
    //   474: aload_2
    //   475: invokespecial 1112	gnu/mapping/WrongType:<init>	(Ljava/lang/ClassCastException;Ljava/lang/String;ILjava/lang/Object;)V
    //   478: athrow
    //   479: aload_2
    //   480: checkcast 1090	gnu/lists/Pair
    //   483: astore_3
    //   484: aload_3
    //   485: invokevirtual 1096	gnu/lists/Pair:getCar	()Ljava/lang/Object;
    //   488: astore_2
    //   489: getstatic 1291	kawa/lib/lists:caddr	Lgnu/expr/GenericProc;
    //   492: aload_2
    //   493: invokevirtual 1261	gnu/mapping/Procedure:apply1	(Ljava/lang/Object;)Ljava/lang/Object;
    //   496: pop
    //   497: getstatic 1294	kawa/lib/lists:cadddr	Lgnu/expr/GenericProc;
    //   500: aload_2
    //   501: invokevirtual 1261	gnu/mapping/Procedure:apply1	(Ljava/lang/Object;)Ljava/lang/Object;
    //   504: astore_2
    //   505: aload_2
    //   506: getstatic 1316	java/lang/Boolean:FALSE	Ljava/lang/Boolean;
    //   509: if_acmpeq +11 -> 520
    //   512: getstatic 1282	kawa/standard/Scheme:applyToArgs	Lgnu/kawa/functions/ApplyToArgs;
    //   515: aload_2
    //   516: invokevirtual 1261	gnu/mapping/Procedure:apply1	(Ljava/lang/Object;)Ljava/lang/Object;
    //   519: pop
    //   520: aload_3
    //   521: invokevirtual 1093	gnu/lists/Pair:getCdr	()Ljava/lang/Object;
    //   524: astore_2
    //   525: goto -432 -> 93
    //   528: astore_1
    //   529: new 1107	gnu/mapping/WrongType
    //   532: dup
    //   533: aload_1
    //   534: ldc_w 1109
    //   537: bipush -2
    //   539: aload_2
    //   540: invokespecial 1112	gnu/mapping/WrongType:<init>	(Ljava/lang/ClassCastException;Ljava/lang/String;ILjava/lang/Object;)V
    //   543: athrow
    //   544: aload_1
    //   545: checkcast 1090	gnu/lists/Pair
    //   548: astore_2
    //   549: aload_2
    //   550: invokevirtual 1096	gnu/lists/Pair:getCar	()Ljava/lang/Object;
    //   553: astore_1
    //   554: getstatic 1291	kawa/lib/lists:caddr	Lgnu/expr/GenericProc;
    //   557: aload_1
    //   558: invokevirtual 1261	gnu/mapping/Procedure:apply1	(Ljava/lang/Object;)Ljava/lang/Object;
    //   561: astore_3
    //   562: getstatic 1294	kawa/lib/lists:cadddr	Lgnu/expr/GenericProc;
    //   565: aload_1
    //   566: invokevirtual 1261	gnu/mapping/Procedure:apply1	(Ljava/lang/Object;)Ljava/lang/Object;
    //   569: pop
    //   570: aload_0
    //   571: getstatic 1322	gnu/kawa/reflect/SlotGet:field	Lgnu/kawa/reflect/SlotGet;
    //   574: aload_0
    //   575: aload_3
    //   576: invokevirtual 1080	gnu/mapping/Procedure:apply2	(Ljava/lang/Object;Ljava/lang/Object;)Ljava/lang/Object;
    //   579: invokevirtual 1325	appinventor/ai_prafulmathur95/whereismycar/Screen1:callInitialize	(Ljava/lang/Object;)V
    //   582: aload_2
    //   583: invokevirtual 1093	gnu/lists/Pair:getCdr	()Ljava/lang/Object;
    //   586: astore_1
    //   587: goto -487 -> 100
    //   590: astore_2
    //   591: new 1107	gnu/mapping/WrongType
    //   594: dup
    //   595: aload_2
    //   596: ldc_w 1109
    //   599: bipush -2
    //   601: aload_1
    //   602: invokespecial 1112	gnu/mapping/WrongType:<init>	(Ljava/lang/ClassCastException;Ljava/lang/String;ILjava/lang/Object;)V
    //   605: athrow
    //   606: astore_2
    //   607: new 1107	gnu/mapping/WrongType
    //   610: dup
    //   611: aload_2
    //   612: ldc_w 1109
    //   615: bipush -2
    //   617: aload_1
    //   618: invokespecial 1112	gnu/mapping/WrongType:<init>	(Ljava/lang/ClassCastException;Ljava/lang/String;ILjava/lang/Object;)V
    //   621: athrow
    // Local variable table:
    //   start	length	slot	name	signature
    //   0	622	0	this	Screen1
    //   26	79	1	localLList	LList
    //   110	18	1	localException	Exception
    //   144	116	1	localObject1	Object
    //   264	23	1	localYailRuntimeError	com.google.appinventor.components.runtime.errors.YailRuntimeError
    //   303	16	1	localObject2	Object
    //   432	6	1	localClassCastException1	ClassCastException
    //   448	6	1	localClassCastException2	ClassCastException
    //   464	6	1	localClassCastException3	ClassCastException
    //   528	17	1	localClassCastException4	ClassCastException
    //   553	65	1	localObject3	Object
    //   83	158	2	localObject4	Object
    //   248	6	2	localClassCastException5	ClassCastException
    //   271	6	2	localClassCastException6	ClassCastException
    //   290	10	2	localPair	Pair
    //   307	17	2	localClassCastException7	ClassCastException
    //   342	241	2	localObject5	Object
    //   590	6	2	localClassCastException8	ClassCastException
    //   606	6	2	localClassCastException9	ClassCastException
    //   131	445	3	localObject6	Object
    //   225	195	4	localObject7	Object
    //   332	127	5	localObject8	Object
    //   377	4	6	localSymbol	Symbol
    // Exception table:
    //   from	to	target	type
    //   6	10	110	java/lang/Exception
    //   195	200	248	java/lang/ClassCastException
    //   34	52	264	com/google/appinventor/components/runtime/errors/YailRuntimeError
    //   52	67	264	com/google/appinventor/components/runtime/errors/YailRuntimeError
    //   67	82	264	com/google/appinventor/components/runtime/errors/YailRuntimeError
    //   84	91	264	com/google/appinventor/components/runtime/errors/YailRuntimeError
    //   93	100	264	com/google/appinventor/components/runtime/errors/YailRuntimeError
    //   100	104	264	com/google/appinventor/components/runtime/errors/YailRuntimeError
    //   195	200	264	com/google/appinventor/components/runtime/errors/YailRuntimeError
    //   200	221	264	com/google/appinventor/components/runtime/errors/YailRuntimeError
    //   221	227	264	com/google/appinventor/components/runtime/errors/YailRuntimeError
    //   227	245	264	com/google/appinventor/components/runtime/errors/YailRuntimeError
    //   249	264	264	com/google/appinventor/components/runtime/errors/YailRuntimeError
    //   272	286	264	com/google/appinventor/components/runtime/errors/YailRuntimeError
    //   286	291	264	com/google/appinventor/components/runtime/errors/YailRuntimeError
    //   291	304	264	com/google/appinventor/components/runtime/errors/YailRuntimeError
    //   308	323	264	com/google/appinventor/components/runtime/errors/YailRuntimeError
    //   323	328	264	com/google/appinventor/components/runtime/errors/YailRuntimeError
    //   328	372	264	com/google/appinventor/components/runtime/errors/YailRuntimeError
    //   372	379	264	com/google/appinventor/components/runtime/errors/YailRuntimeError
    //   379	410	264	com/google/appinventor/components/runtime/errors/YailRuntimeError
    //   410	416	264	com/google/appinventor/components/runtime/errors/YailRuntimeError
    //   416	429	264	com/google/appinventor/components/runtime/errors/YailRuntimeError
    //   433	448	264	com/google/appinventor/components/runtime/errors/YailRuntimeError
    //   449	464	264	com/google/appinventor/components/runtime/errors/YailRuntimeError
    //   465	479	264	com/google/appinventor/components/runtime/errors/YailRuntimeError
    //   479	484	264	com/google/appinventor/components/runtime/errors/YailRuntimeError
    //   484	520	264	com/google/appinventor/components/runtime/errors/YailRuntimeError
    //   520	525	264	com/google/appinventor/components/runtime/errors/YailRuntimeError
    //   529	544	264	com/google/appinventor/components/runtime/errors/YailRuntimeError
    //   544	549	264	com/google/appinventor/components/runtime/errors/YailRuntimeError
    //   549	587	264	com/google/appinventor/components/runtime/errors/YailRuntimeError
    //   591	606	264	com/google/appinventor/components/runtime/errors/YailRuntimeError
    //   221	227	271	java/lang/ClassCastException
    //   286	291	307	java/lang/ClassCastException
    //   323	328	432	java/lang/ClassCastException
    //   372	379	448	java/lang/ClassCastException
    //   410	416	464	java/lang/ClassCastException
    //   479	484	528	java/lang/ClassCastException
    //   544	549	590	java/lang/ClassCastException
    //   127	132	606	java/lang/ClassCastException
  }
  
  public Object LocationSensor1$LocationChanged(Object paramObject1, Object paramObject2, Object paramObject3)
  {
    paramObject1 = runtime.sanitizeComponentData(paramObject1);
    paramObject2 = runtime.sanitizeComponentData(paramObject2);
    runtime.sanitizeComponentData(paramObject3);
    runtime.setThisForm();
    runtime.setAndCoerceProperty$Ex(Lit67, Lit25, runtime.getProperty$1(Lit16, Lit98), Lit5);
    runtime.setAndCoerceProperty$Ex(Lit79, Lit25, paramObject1, Lit5);
    runtime.setAndCoerceProperty$Ex(Lit87, Lit25, paramObject2, Lit5);
    return runtime.setAndCoerceProperty$Ex(Lit94, Lit17, Boolean.TRUE, Lit14);
  }
  
  public Object RememberButton$Click()
  {
    runtime.setThisForm();
    runtime.setAndCoerceProperty$Ex(Lit24, Lit25, runtime.getProperty$1(Lit16, Lit98), Lit5);
    runtime.setAndCoerceProperty$Ex(Lit26, Lit25, runtime.getProperty$1(Lit16, Lit99), Lit5);
    runtime.setAndCoerceProperty$Ex(Lit29, Lit25, runtime.getProperty$1(Lit16, Lit100), Lit5);
    runtime.callComponentMethod(Lit18, Lit101, LList.list2("address", runtime.getProperty$1(Lit16, Lit98)), Lit102);
    runtime.callComponentMethod(Lit27, Lit101, LList.list2("lat", runtime.getProperty$1(Lit16, Lit99)), Lit103);
    runtime.callComponentMethod(Lit30, Lit101, LList.list2("long", runtime.getProperty$1(Lit16, Lit100)), Lit104);
    return runtime.setAndCoerceProperty$Ex(Lit32, Lit17, Boolean.TRUE, Lit14);
  }
  
  public Object Screen1$Initialize()
  {
    runtime.setThisForm();
    runtime.setAndCoerceProperty$Ex(Lit16, Lit17, Boolean.TRUE, Lit14);
    runtime.addGlobalVarToCurrentFormEnvironment(Lit3, runtime.callComponentMethod(Lit18, Lit19, LList.list2("address", ""), Lit20));
    if (runtime.callYailPrimitive(Scheme.numGrt, LList.list2(runtime.callYailPrimitive(strings.string$Mnlength, LList.list1(runtime.lookupGlobalVarInCurrentFormEnvironment(Lit3, runtime.$Stthe$Mnnull$Mnvalue$St)), Lit21, "length"), Lit22), Lit23, ">") != Boolean.FALSE)
    {
      runtime.setAndCoerceProperty$Ex(Lit24, Lit25, runtime.lookupGlobalVarInCurrentFormEnvironment(Lit3, runtime.$Stthe$Mnnull$Mnvalue$St), Lit5);
      runtime.setAndCoerceProperty$Ex(Lit26, Lit25, runtime.callComponentMethod(Lit27, Lit19, LList.list2("lat", ""), Lit28), Lit5);
      runtime.setAndCoerceProperty$Ex(Lit29, Lit25, runtime.callComponentMethod(Lit30, Lit19, LList.list2("long", ""), Lit31), Lit5);
      return runtime.setAndCoerceProperty$Ex(Lit32, Lit17, Boolean.TRUE, Lit14);
    }
    return Values.empty;
  }
  
  public void addToComponents(Object paramObject1, Object paramObject2, Object paramObject3, Object paramObject4)
  {
    this.components$Mnto$Mncreate = lists.cons(LList.list4(paramObject1, paramObject2, paramObject3, paramObject4), this.components$Mnto$Mncreate);
  }
  
  public void addToEvents(Object paramObject1, Object paramObject2)
  {
    this.events$Mnto$Mnregister = lists.cons(lists.cons(paramObject1, paramObject2), this.events$Mnto$Mnregister);
  }
  
  public void addToFormDoAfterCreation(Object paramObject)
  {
    this.form$Mndo$Mnafter$Mncreation = lists.cons(paramObject, this.form$Mndo$Mnafter$Mncreation);
  }
  
  public void addToFormEnvironment(Symbol paramSymbol, Object paramObject)
  {
    androidLogForm(Format.formatToString(0, new Object[] { "Adding ~A to env ~A with value ~A", paramSymbol, this.form$Mnenvironment, paramObject }));
    this.form$Mnenvironment.put(paramSymbol, paramObject);
  }
  
  public void addToGlobalVarEnvironment(Symbol paramSymbol, Object paramObject)
  {
    androidLogForm(Format.formatToString(0, new Object[] { "Adding ~A to env ~A with value ~A", paramSymbol, this.global$Mnvar$Mnenvironment, paramObject }));
    this.global$Mnvar$Mnenvironment.put(paramSymbol, paramObject);
  }
  
  public void addToGlobalVars(Object paramObject1, Object paramObject2)
  {
    this.global$Mnvars$Mnto$Mncreate = lists.cons(LList.list2(paramObject1, paramObject2), this.global$Mnvars$Mnto$Mncreate);
  }
  
  public void androidLogForm(Object paramObject) {}
  
  public Object directionbutton$Click()
  {
    
    if (runtime.processAndDelayed$V(new Object[] { lambda$Fn42, lambda$Fn43 }) != Boolean.FALSE)
    {
      runtime.setAndCoerceProperty$Ex(Lit142, Lit143, runtime.callYailPrimitive(strings.string$Mnappend, LList.list4("http://maps.google.com/maps?saddr=", runtime.getProperty$1(Lit79, Lit25), ",", runtime.getProperty$1(Lit87, Lit25)), Lit144, "join"), Lit5);
      return runtime.callComponentMethod(Lit142, Lit145, LList.Empty, LList.Empty);
    }
    SimpleSymbol localSimpleSymbol1 = Lit142;
    SimpleSymbol localSimpleSymbol2 = Lit143;
    ModuleMethod localModuleMethod = strings.string$Mnappend;
    Pair localPair = LList.list1("http://maps.google.com/maps?saddr=");
    LList.chain1(LList.chain1(LList.chain1(LList.chain4(localPair, runtime.getProperty$1(Lit79, Lit25), ",", runtime.getProperty$1(Lit87, Lit25), "&daddr="), runtime.getProperty$1(Lit26, Lit25)), ","), runtime.getProperty$1(Lit29, Lit25));
    runtime.setAndCoerceProperty$Ex(localSimpleSymbol1, localSimpleSymbol2, runtime.callYailPrimitive(localModuleMethod, localPair, Lit146, "join"), Lit5);
    return runtime.callComponentMethod(Lit142, Lit145, LList.Empty, LList.Empty);
  }
  
  public boolean dispatchEvent(Component paramComponent, String paramString1, String paramString2, Object[] paramArrayOfObject)
  {
    boolean bool = false;
    SimpleSymbol localSimpleSymbol = misc.string$To$Symbol(paramString1);
    if (isBoundInFormEnvironment(localSimpleSymbol))
    {
      if (lookupInFormEnvironment(localSimpleSymbol) == paramComponent) {
        paramComponent = lookupHandler(paramString1, paramString2);
      }
      try
      {
        Scheme.apply.apply2(paramComponent, LList.makeList(paramArrayOfObject, 0));
        bool = true;
        return bool;
      }
      catch (Throwable paramComponent)
      {
        androidLogForm(paramComponent.getMessage());
        paramComponent.printStackTrace();
        processException(paramComponent);
        return false;
      }
    }
    EventDispatcher.unregisterEventForDelegation(this, paramString1, paramString2);
    return false;
  }
  
  public boolean isBoundInFormEnvironment(Symbol paramSymbol)
  {
    return this.form$Mnenvironment.isBound(paramSymbol);
  }
  
  public Object lookupHandler(Object paramObject1, Object paramObject2)
  {
    Object localObject = null;
    if (paramObject1 == null)
    {
      paramObject1 = null;
      if (paramObject2 != null) {
        break label35;
      }
    }
    label35:
    for (paramObject2 = localObject;; paramObject2 = paramObject2.toString())
    {
      return lookupInFormEnvironment(misc.string$To$Symbol(EventDispatcher.makeFullEventName((String)paramObject1, (String)paramObject2)));
      paramObject1 = paramObject1.toString();
      break;
    }
  }
  
  public Object lookupInFormEnvironment(Symbol paramSymbol)
  {
    return lookupInFormEnvironment(paramSymbol, Boolean.FALSE);
  }
  
  public Object lookupInFormEnvironment(Symbol paramSymbol, Object paramObject)
  {
    int i;
    if (this.form$Mnenvironment == null)
    {
      i = 1;
      i = i + 1 & 0x1;
      if (i == 0) {
        break label46;
      }
      if (!this.form$Mnenvironment.isBound(paramSymbol)) {}
    }
    for (;;)
    {
      paramObject = this.form$Mnenvironment.get(paramSymbol);
      label46:
      do
      {
        return paramObject;
        i = 0;
        break;
      } while (i == 0);
    }
  }
  
  /* Error */
  public void processException(Object paramObject)
  {
    // Byte code:
    //   0: aload_1
    //   1: checkcast 1421	java/lang/Throwable
    //   4: astore_2
    //   5: aload_2
    //   6: invokestatic 1453	com/google/appinventor/components/runtime/ReplApplication:reportError	(Ljava/lang/Throwable;)V
    //   9: getstatic 1282	kawa/standard/Scheme:applyToArgs	Lgnu/kawa/functions/ApplyToArgs;
    //   12: getstatic 1459	gnu/kawa/functions/GetNamedPart:getNamedPart	Lgnu/kawa/functions/GetNamedPart;
    //   15: aload_1
    //   16: getstatic 861	appinventor/ai_prafulmathur95/whereismycar/Screen1:Lit1	Lgnu/mapping/SimpleSymbol;
    //   19: invokevirtual 1080	gnu/mapping/Procedure:apply2	(Ljava/lang/Object;Ljava/lang/Object;)Ljava/lang/Object;
    //   22: invokevirtual 1261	gnu/mapping/Procedure:apply1	(Ljava/lang/Object;)Ljava/lang/Object;
    //   25: astore_2
    //   26: aload_2
    //   27: ifnonnull +30 -> 57
    //   30: aconst_null
    //   31: astore_2
    //   32: aload_1
    //   33: instanceof 1209
    //   36: ifeq +29 -> 65
    //   39: aload_1
    //   40: checkcast 1209	com/google/appinventor/components/runtime/errors/YailRuntimeError
    //   43: invokevirtual 1462	com/google/appinventor/components/runtime/errors/YailRuntimeError:getErrorType	()Ljava/lang/String;
    //   46: astore_1
    //   47: aload_0
    //   48: aload_2
    //   49: aload_1
    //   50: ldc_w 1464
    //   53: invokestatic 1470	com/google/appinventor/components/runtime/util/RuntimeErrorAlert:alert	(Ljava/lang/Object;Ljava/lang/String;Ljava/lang/String;Ljava/lang/String;)V
    //   56: return
    //   57: aload_2
    //   58: invokevirtual 1275	java/lang/Object:toString	()Ljava/lang/String;
    //   61: astore_2
    //   62: goto -30 -> 32
    //   65: ldc_w 1472
    //   68: astore_1
    //   69: goto -22 -> 47
    //   72: astore_2
    //   73: new 1107	gnu/mapping/WrongType
    //   76: dup
    //   77: aload_2
    //   78: ldc_w 1474
    //   81: iconst_1
    //   82: aload_1
    //   83: invokespecial 1112	gnu/mapping/WrongType:<init>	(Ljava/lang/ClassCastException;Ljava/lang/String;ILjava/lang/Object;)V
    //   86: athrow
    // Local variable table:
    //   start	length	slot	name	signature
    //   0	87	0	this	Screen1
    //   0	87	1	paramObject	Object
    //   4	58	2	localObject	Object
    //   72	6	2	localClassCastException	ClassCastException
    // Exception table:
    //   from	to	target	type
    //   0	5	72	java/lang/ClassCastException
  }
  
  public void run()
  {
    CallContext localCallContext = CallContext.getInstance();
    Consumer localConsumer = localCallContext.consumer;
    localCallContext.consumer = VoidConsumer.instance;
    try
    {
      run(localCallContext);
      localThrowable1 = null;
    }
    catch (Throwable localThrowable2)
    {
      Throwable localThrowable1;
      for (;;) {}
    }
    ModuleBody.runCleanup(localCallContext, localThrowable1, localConsumer);
  }
  
  /* Error */
  public final void run(CallContext paramCallContext)
  {
    // Byte code:
    //   0: aload_1
    //   1: getfield 1483	gnu/mapping/CallContext:consumer	Lgnu/lists/Consumer;
    //   4: astore_2
    //   5: ldc_w 1500
    //   8: invokestatic 1506	kawa/standard/require:find	(Ljava/lang/String;)Ljava/lang/Object;
    //   11: astore_1
    //   12: aload_1
    //   13: checkcast 6	java/lang/Runnable
    //   16: astore_3
    //   17: aload_3
    //   18: invokeinterface 1507 1 0
    //   23: aload_0
    //   24: getstatic 1316	java/lang/Boolean:FALSE	Ljava/lang/Boolean;
    //   27: putfield 1509	appinventor/ai_prafulmathur95/whereismycar/Screen1:$Stdebug$Mnform$St	Ljava/lang/Boolean;
    //   30: aload_0
    //   31: getstatic 864	appinventor/ai_prafulmathur95/whereismycar/Screen1:Lit0	Lgnu/mapping/SimpleSymbol;
    //   34: invokestatic 1102	kawa/lib/misc:symbol$To$String	(Lgnu/mapping/Symbol;)Ljava/lang/String;
    //   37: invokestatic 1512	gnu/mapping/Environment:make	(Ljava/lang/String;)Lgnu/mapping/SimpleEnvironment;
    //   40: putfield 1387	appinventor/ai_prafulmathur95/whereismycar/Screen1:form$Mnenvironment	Lgnu/mapping/Environment;
    //   43: iconst_2
    //   44: anewarray 1272	java/lang/Object
    //   47: dup
    //   48: iconst_0
    //   49: getstatic 864	appinventor/ai_prafulmathur95/whereismycar/Screen1:Lit0	Lgnu/mapping/SimpleSymbol;
    //   52: invokestatic 1102	kawa/lib/misc:symbol$To$String	(Lgnu/mapping/Symbol;)Ljava/lang/String;
    //   55: aastore
    //   56: dup
    //   57: iconst_1
    //   58: ldc_w 1514
    //   61: aastore
    //   62: invokestatic 1518	kawa/lib/strings:stringAppend	([Ljava/lang/Object;)Lgnu/lists/FString;
    //   65: astore_1
    //   66: aload_1
    //   67: ifnonnull +1369 -> 1436
    //   70: aconst_null
    //   71: astore_1
    //   72: aload_0
    //   73: aload_1
    //   74: invokestatic 1512	gnu/mapping/Environment:make	(Ljava/lang/String;)Lgnu/mapping/SimpleEnvironment;
    //   77: putfield 1400	appinventor/ai_prafulmathur95/whereismycar/Screen1:global$Mnvar$Mnenvironment	Lgnu/mapping/Environment;
    //   80: aconst_null
    //   81: putstatic 1224	appinventor/ai_prafulmathur95/whereismycar/Screen1:Screen1	Lappinventor/ai_prafulmathur95/whereismycar/Screen1;
    //   84: aload_0
    //   85: getstatic 864	appinventor/ai_prafulmathur95/whereismycar/Screen1:Lit0	Lgnu/mapping/SimpleSymbol;
    //   88: putfield 1520	appinventor/ai_prafulmathur95/whereismycar/Screen1:form$Mnname$Mnsymbol	Lgnu/mapping/Symbol;
    //   91: aload_0
    //   92: getstatic 423	gnu/lists/LList:Empty	Lgnu/lists/LList;
    //   95: putfield 1230	appinventor/ai_prafulmathur95/whereismycar/Screen1:events$Mnto$Mnregister	Lgnu/lists/LList;
    //   98: aload_0
    //   99: getstatic 423	gnu/lists/LList:Empty	Lgnu/lists/LList;
    //   102: putfield 1245	appinventor/ai_prafulmathur95/whereismycar/Screen1:components$Mnto$Mncreate	Lgnu/lists/LList;
    //   105: aload_0
    //   106: getstatic 423	gnu/lists/LList:Empty	Lgnu/lists/LList;
    //   109: putfield 1235	appinventor/ai_prafulmathur95/whereismycar/Screen1:global$Mnvars$Mnto$Mncreate	Lgnu/lists/LList;
    //   112: aload_0
    //   113: getstatic 423	gnu/lists/LList:Empty	Lgnu/lists/LList;
    //   116: putfield 1243	appinventor/ai_prafulmathur95/whereismycar/Screen1:form$Mndo$Mnafter$Mncreation	Lgnu/lists/LList;
    //   119: ldc_w 1500
    //   122: invokestatic 1506	kawa/standard/require:find	(Ljava/lang/String;)Ljava/lang/Object;
    //   125: astore_1
    //   126: aload_1
    //   127: checkcast 6	java/lang/Runnable
    //   130: astore_3
    //   131: aload_3
    //   132: invokeinterface 1507 1 0
    //   137: getstatic 1523	com/google/youngandroid/runtime:$Stthis$Mnis$Mnthe$Mnrepl$St	Ljava/lang/Object;
    //   140: getstatic 1316	java/lang/Boolean:FALSE	Ljava/lang/Boolean;
    //   143: if_acmpeq +1301 -> 1444
    //   146: getstatic 853	appinventor/ai_prafulmathur95/whereismycar/Screen1:Lit3	Lgnu/mapping/SimpleSymbol;
    //   149: ldc_w 1141
    //   152: invokestatic 1344	com/google/youngandroid/runtime:addGlobalVarToCurrentFormEnvironment	(Lgnu/mapping/Symbol;Ljava/lang/Object;)Ljava/lang/Object;
    //   155: aload_2
    //   156: invokestatic 1527	gnu/mapping/Values:writeValues	(Ljava/lang/Object;Lgnu/lists/Consumer;)V
    //   159: getstatic 1523	com/google/youngandroid/runtime:$Stthis$Mnis$Mnthe$Mnrepl$St	Ljava/lang/Object;
    //   162: getstatic 1316	java/lang/Boolean:FALSE	Ljava/lang/Boolean;
    //   165: if_acmpeq +1292 -> 1457
    //   168: getstatic 864	appinventor/ai_prafulmathur95/whereismycar/Screen1:Lit0	Lgnu/mapping/SimpleSymbol;
    //   171: getstatic 849	appinventor/ai_prafulmathur95/whereismycar/Screen1:Lit4	Lgnu/mapping/SimpleSymbol;
    //   174: ldc_w 1154
    //   177: getstatic 418	appinventor/ai_prafulmathur95/whereismycar/Screen1:Lit5	Lgnu/mapping/SimpleSymbol;
    //   180: invokestatic 1032	com/google/youngandroid/runtime:setAndCoerceProperty$Ex	(Ljava/lang/Object;Ljava/lang/Object;Ljava/lang/Object;Ljava/lang/Object;)Ljava/lang/Object;
    //   183: pop
    //   184: getstatic 864	appinventor/ai_prafulmathur95/whereismycar/Screen1:Lit0	Lgnu/mapping/SimpleSymbol;
    //   187: getstatic 845	appinventor/ai_prafulmathur95/whereismycar/Screen1:Lit6	Lgnu/mapping/SimpleSymbol;
    //   190: getstatic 841	appinventor/ai_prafulmathur95/whereismycar/Screen1:Lit7	Lgnu/math/IntNum;
    //   193: getstatic 783	appinventor/ai_prafulmathur95/whereismycar/Screen1:Lit8	Lgnu/mapping/SimpleSymbol;
    //   196: invokestatic 1032	com/google/youngandroid/runtime:setAndCoerceProperty$Ex	(Ljava/lang/Object;Ljava/lang/Object;Ljava/lang/Object;Ljava/lang/Object;)Ljava/lang/Object;
    //   199: pop
    //   200: getstatic 864	appinventor/ai_prafulmathur95/whereismycar/Screen1:Lit0	Lgnu/mapping/SimpleSymbol;
    //   203: getstatic 838	appinventor/ai_prafulmathur95/whereismycar/Screen1:Lit9	Lgnu/mapping/SimpleSymbol;
    //   206: ldc_w 1156
    //   209: getstatic 418	appinventor/ai_prafulmathur95/whereismycar/Screen1:Lit5	Lgnu/mapping/SimpleSymbol;
    //   212: invokestatic 1032	com/google/youngandroid/runtime:setAndCoerceProperty$Ex	(Ljava/lang/Object;Ljava/lang/Object;Ljava/lang/Object;Ljava/lang/Object;)Ljava/lang/Object;
    //   215: pop
    //   216: getstatic 864	appinventor/ai_prafulmathur95/whereismycar/Screen1:Lit0	Lgnu/mapping/SimpleSymbol;
    //   219: getstatic 834	appinventor/ai_prafulmathur95/whereismycar/Screen1:Lit10	Lgnu/mapping/SimpleSymbol;
    //   222: ldc_w 1158
    //   225: getstatic 418	appinventor/ai_prafulmathur95/whereismycar/Screen1:Lit5	Lgnu/mapping/SimpleSymbol;
    //   228: invokestatic 1032	com/google/youngandroid/runtime:setAndCoerceProperty$Ex	(Ljava/lang/Object;Ljava/lang/Object;Ljava/lang/Object;Ljava/lang/Object;)Ljava/lang/Object;
    //   231: pop
    //   232: getstatic 864	appinventor/ai_prafulmathur95/whereismycar/Screen1:Lit0	Lgnu/mapping/SimpleSymbol;
    //   235: getstatic 830	appinventor/ai_prafulmathur95/whereismycar/Screen1:Lit11	Lgnu/mapping/SimpleSymbol;
    //   238: ldc_w 1160
    //   241: getstatic 418	appinventor/ai_prafulmathur95/whereismycar/Screen1:Lit5	Lgnu/mapping/SimpleSymbol;
    //   244: invokestatic 1032	com/google/youngandroid/runtime:setAndCoerceProperty$Ex	(Ljava/lang/Object;Ljava/lang/Object;Ljava/lang/Object;Ljava/lang/Object;)Ljava/lang/Object;
    //   247: pop
    //   248: getstatic 864	appinventor/ai_prafulmathur95/whereismycar/Screen1:Lit0	Lgnu/mapping/SimpleSymbol;
    //   251: getstatic 826	appinventor/ai_prafulmathur95/whereismycar/Screen1:Lit12	Lgnu/mapping/SimpleSymbol;
    //   254: ldc_w 1162
    //   257: getstatic 418	appinventor/ai_prafulmathur95/whereismycar/Screen1:Lit5	Lgnu/mapping/SimpleSymbol;
    //   260: invokestatic 1032	com/google/youngandroid/runtime:setAndCoerceProperty$Ex	(Ljava/lang/Object;Ljava/lang/Object;Ljava/lang/Object;Ljava/lang/Object;)Ljava/lang/Object;
    //   263: pop
    //   264: getstatic 864	appinventor/ai_prafulmathur95/whereismycar/Screen1:Lit0	Lgnu/mapping/SimpleSymbol;
    //   267: getstatic 822	appinventor/ai_prafulmathur95/whereismycar/Screen1:Lit13	Lgnu/mapping/SimpleSymbol;
    //   270: getstatic 1167	java/lang/Boolean:TRUE	Ljava/lang/Boolean;
    //   273: getstatic 818	appinventor/ai_prafulmathur95/whereismycar/Screen1:Lit14	Lgnu/mapping/SimpleSymbol;
    //   276: invokestatic 1032	com/google/youngandroid/runtime:setAndCoerceProperty$Ex	(Ljava/lang/Object;Ljava/lang/Object;Ljava/lang/Object;Ljava/lang/Object;)Ljava/lang/Object;
    //   279: pop
    //   280: getstatic 864	appinventor/ai_prafulmathur95/whereismycar/Screen1:Lit0	Lgnu/mapping/SimpleSymbol;
    //   283: getstatic 814	appinventor/ai_prafulmathur95/whereismycar/Screen1:Lit15	Lgnu/mapping/SimpleSymbol;
    //   286: ldc_w 1169
    //   289: getstatic 418	appinventor/ai_prafulmathur95/whereismycar/Screen1:Lit5	Lgnu/mapping/SimpleSymbol;
    //   292: invokestatic 1032	com/google/youngandroid/runtime:setAndCoerceProperty$Ex	(Ljava/lang/Object;Ljava/lang/Object;Ljava/lang/Object;Ljava/lang/Object;)Ljava/lang/Object;
    //   295: aload_2
    //   296: invokestatic 1527	gnu/mapping/Values:writeValues	(Ljava/lang/Object;Lgnu/lists/Consumer;)V
    //   299: getstatic 1523	com/google/youngandroid/runtime:$Stthis$Mnis$Mnthe$Mnrepl$St	Ljava/lang/Object;
    //   302: getstatic 1316	java/lang/Boolean:FALSE	Ljava/lang/Boolean;
    //   305: if_acmpeq +1169 -> 1474
    //   308: getstatic 749	appinventor/ai_prafulmathur95/whereismycar/Screen1:Lit33	Lgnu/mapping/SimpleSymbol;
    //   311: aload_0
    //   312: getfield 933	appinventor/ai_prafulmathur95/whereismycar/Screen1:Screen1$Initialize	Lgnu/expr/ModuleMethod;
    //   315: invokestatic 1530	com/google/youngandroid/runtime:addToCurrentFormEnvironment	(Lgnu/mapping/Symbol;Ljava/lang/Object;)Ljava/lang/Object;
    //   318: pop
    //   319: getstatic 1523	com/google/youngandroid/runtime:$Stthis$Mnis$Mnthe$Mnrepl$St	Ljava/lang/Object;
    //   322: getstatic 1316	java/lang/Boolean:FALSE	Ljava/lang/Boolean;
    //   325: if_acmpeq +1163 -> 1488
    //   328: getstatic 1533	com/google/youngandroid/runtime:$Stthis$Mnform$St	Ljava/lang/Object;
    //   331: checkcast 1535	com/google/appinventor/components/runtime/HandlesEventDispatching
    //   334: ldc_w 862
    //   337: ldc_w 744
    //   340: invokestatic 1270	com/google/appinventor/components/runtime/EventDispatcher:registerEventForDelegation	(Lcom/google/appinventor/components/runtime/HandlesEventDispatching;Ljava/lang/String;Ljava/lang/String;)V
    //   343: aload_0
    //   344: aconst_null
    //   345: putfield 1537	appinventor/ai_prafulmathur95/whereismycar/Screen1:Canvas2	Lcom/google/appinventor/components/runtime/Canvas;
    //   348: getstatic 1523	com/google/youngandroid/runtime:$Stthis$Mnis$Mnthe$Mnrepl$St	Ljava/lang/Object;
    //   351: getstatic 1316	java/lang/Boolean:FALSE	Ljava/lang/Boolean;
    //   354: if_acmpeq +1147 -> 1501
    //   357: getstatic 864	appinventor/ai_prafulmathur95/whereismycar/Screen1:Lit0	Lgnu/mapping/SimpleSymbol;
    //   360: getstatic 742	appinventor/ai_prafulmathur95/whereismycar/Screen1:Lit35	Lgnu/lists/FString;
    //   363: getstatic 740	appinventor/ai_prafulmathur95/whereismycar/Screen1:Lit36	Lgnu/mapping/SimpleSymbol;
    //   366: getstatic 935	appinventor/ai_prafulmathur95/whereismycar/Screen1:lambda$Fn4	Lgnu/expr/ModuleMethod;
    //   369: invokestatic 1540	com/google/youngandroid/runtime:addComponentWithinRepl	(Ljava/lang/Object;Ljava/lang/Object;Ljava/lang/Object;Ljava/lang/Object;)Ljava/lang/Object;
    //   372: aload_2
    //   373: invokestatic 1527	gnu/mapping/Values:writeValues	(Ljava/lang/Object;Lgnu/lists/Consumer;)V
    //   376: aload_0
    //   377: aconst_null
    //   378: putfield 1542	appinventor/ai_prafulmathur95/whereismycar/Screen1:HorizontalArrangement5	Lcom/google/appinventor/components/runtime/HorizontalArrangement;
    //   381: getstatic 1523	com/google/youngandroid/runtime:$Stthis$Mnis$Mnthe$Mnrepl$St	Ljava/lang/Object;
    //   384: getstatic 1316	java/lang/Boolean:FALSE	Ljava/lang/Boolean;
    //   387: if_acmpeq +1133 -> 1520
    //   390: getstatic 864	appinventor/ai_prafulmathur95/whereismycar/Screen1:Lit0	Lgnu/mapping/SimpleSymbol;
    //   393: getstatic 723	appinventor/ai_prafulmathur95/whereismycar/Screen1:Lit42	Lgnu/lists/FString;
    //   396: getstatic 721	appinventor/ai_prafulmathur95/whereismycar/Screen1:Lit43	Lgnu/mapping/SimpleSymbol;
    //   399: getstatic 939	appinventor/ai_prafulmathur95/whereismycar/Screen1:lambda$Fn6	Lgnu/expr/ModuleMethod;
    //   402: invokestatic 1540	com/google/youngandroid/runtime:addComponentWithinRepl	(Ljava/lang/Object;Ljava/lang/Object;Ljava/lang/Object;Ljava/lang/Object;)Ljava/lang/Object;
    //   405: aload_2
    //   406: invokestatic 1527	gnu/mapping/Values:writeValues	(Ljava/lang/Object;Lgnu/lists/Consumer;)V
    //   409: aload_0
    //   410: aconst_null
    //   411: putfield 1544	appinventor/ai_prafulmathur95/whereismycar/Screen1:Canvas1	Lcom/google/appinventor/components/runtime/Canvas;
    //   414: getstatic 1523	com/google/youngandroid/runtime:$Stthis$Mnis$Mnthe$Mnrepl$St	Ljava/lang/Object;
    //   417: getstatic 1316	java/lang/Boolean:FALSE	Ljava/lang/Boolean;
    //   420: if_acmpeq +1119 -> 1539
    //   423: getstatic 721	appinventor/ai_prafulmathur95/whereismycar/Screen1:Lit43	Lgnu/mapping/SimpleSymbol;
    //   426: getstatic 716	appinventor/ai_prafulmathur95/whereismycar/Screen1:Lit45	Lgnu/lists/FString;
    //   429: getstatic 714	appinventor/ai_prafulmathur95/whereismycar/Screen1:Lit46	Lgnu/mapping/SimpleSymbol;
    //   432: getstatic 943	appinventor/ai_prafulmathur95/whereismycar/Screen1:lambda$Fn8	Lgnu/expr/ModuleMethod;
    //   435: invokestatic 1540	com/google/youngandroid/runtime:addComponentWithinRepl	(Ljava/lang/Object;Ljava/lang/Object;Ljava/lang/Object;Ljava/lang/Object;)Ljava/lang/Object;
    //   438: aload_2
    //   439: invokestatic 1527	gnu/mapping/Values:writeValues	(Ljava/lang/Object;Lgnu/lists/Consumer;)V
    //   442: aload_0
    //   443: aconst_null
    //   444: putfield 1546	appinventor/ai_prafulmathur95/whereismycar/Screen1:Label1	Lcom/google/appinventor/components/runtime/Label;
    //   447: getstatic 1523	com/google/youngandroid/runtime:$Stthis$Mnis$Mnthe$Mnrepl$St	Ljava/lang/Object;
    //   450: getstatic 1316	java/lang/Boolean:FALSE	Ljava/lang/Boolean;
    //   453: if_acmpeq +1105 -> 1558
    //   456: getstatic 721	appinventor/ai_prafulmathur95/whereismycar/Screen1:Lit43	Lgnu/mapping/SimpleSymbol;
    //   459: getstatic 705	appinventor/ai_prafulmathur95/whereismycar/Screen1:Lit49	Lgnu/lists/FString;
    //   462: getstatic 703	appinventor/ai_prafulmathur95/whereismycar/Screen1:Lit50	Lgnu/mapping/SimpleSymbol;
    //   465: getstatic 947	appinventor/ai_prafulmathur95/whereismycar/Screen1:lambda$Fn10	Lgnu/expr/ModuleMethod;
    //   468: invokestatic 1540	com/google/youngandroid/runtime:addComponentWithinRepl	(Ljava/lang/Object;Ljava/lang/Object;Ljava/lang/Object;Ljava/lang/Object;)Ljava/lang/Object;
    //   471: aload_2
    //   472: invokestatic 1527	gnu/mapping/Values:writeValues	(Ljava/lang/Object;Lgnu/lists/Consumer;)V
    //   475: aload_0
    //   476: aconst_null
    //   477: putfield 1548	appinventor/ai_prafulmathur95/whereismycar/Screen1:HorizontalArrangement1	Lcom/google/appinventor/components/runtime/HorizontalArrangement;
    //   480: getstatic 1523	com/google/youngandroid/runtime:$Stthis$Mnis$Mnthe$Mnrepl$St	Ljava/lang/Object;
    //   483: getstatic 1316	java/lang/Boolean:FALSE	Ljava/lang/Boolean;
    //   486: if_acmpeq +1091 -> 1577
    //   489: getstatic 864	appinventor/ai_prafulmathur95/whereismycar/Screen1:Lit0	Lgnu/mapping/SimpleSymbol;
    //   492: getstatic 680	appinventor/ai_prafulmathur95/whereismycar/Screen1:Lit58	Lgnu/lists/FString;
    //   495: getstatic 678	appinventor/ai_prafulmathur95/whereismycar/Screen1:Lit59	Lgnu/mapping/SimpleSymbol;
    //   498: getstatic 1316	java/lang/Boolean:FALSE	Ljava/lang/Boolean;
    //   501: invokestatic 1540	com/google/youngandroid/runtime:addComponentWithinRepl	(Ljava/lang/Object;Ljava/lang/Object;Ljava/lang/Object;Ljava/lang/Object;)Ljava/lang/Object;
    //   504: aload_2
    //   505: invokestatic 1527	gnu/mapping/Values:writeValues	(Ljava/lang/Object;Lgnu/lists/Consumer;)V
    //   508: aload_0
    //   509: aconst_null
    //   510: putfield 1550	appinventor/ai_prafulmathur95/whereismycar/Screen1:Label2	Lcom/google/appinventor/components/runtime/Label;
    //   513: getstatic 1523	com/google/youngandroid/runtime:$Stthis$Mnis$Mnthe$Mnrepl$St	Ljava/lang/Object;
    //   516: getstatic 1316	java/lang/Boolean:FALSE	Ljava/lang/Boolean;
    //   519: if_acmpeq +1077 -> 1596
    //   522: getstatic 678	appinventor/ai_prafulmathur95/whereismycar/Screen1:Lit59	Lgnu/mapping/SimpleSymbol;
    //   525: getstatic 673	appinventor/ai_prafulmathur95/whereismycar/Screen1:Lit61	Lgnu/lists/FString;
    //   528: getstatic 671	appinventor/ai_prafulmathur95/whereismycar/Screen1:Lit62	Lgnu/mapping/SimpleSymbol;
    //   531: getstatic 951	appinventor/ai_prafulmathur95/whereismycar/Screen1:lambda$Fn12	Lgnu/expr/ModuleMethod;
    //   534: invokestatic 1540	com/google/youngandroid/runtime:addComponentWithinRepl	(Ljava/lang/Object;Ljava/lang/Object;Ljava/lang/Object;Ljava/lang/Object;)Ljava/lang/Object;
    //   537: aload_2
    //   538: invokestatic 1527	gnu/mapping/Values:writeValues	(Ljava/lang/Object;Lgnu/lists/Consumer;)V
    //   541: aload_0
    //   542: aconst_null
    //   543: putfield 1552	appinventor/ai_prafulmathur95/whereismycar/Screen1:currentaddressdatalabel	Lcom/google/appinventor/components/runtime/Label;
    //   546: getstatic 1523	com/google/youngandroid/runtime:$Stthis$Mnis$Mnthe$Mnrepl$St	Ljava/lang/Object;
    //   549: getstatic 1316	java/lang/Boolean:FALSE	Ljava/lang/Boolean;
    //   552: if_acmpeq +1063 -> 1615
    //   555: getstatic 678	appinventor/ai_prafulmathur95/whereismycar/Screen1:Lit59	Lgnu/mapping/SimpleSymbol;
    //   558: getstatic 662	appinventor/ai_prafulmathur95/whereismycar/Screen1:Lit66	Lgnu/lists/FString;
    //   561: getstatic 660	appinventor/ai_prafulmathur95/whereismycar/Screen1:Lit67	Lgnu/mapping/SimpleSymbol;
    //   564: getstatic 955	appinventor/ai_prafulmathur95/whereismycar/Screen1:lambda$Fn14	Lgnu/expr/ModuleMethod;
    //   567: invokestatic 1540	com/google/youngandroid/runtime:addComponentWithinRepl	(Ljava/lang/Object;Ljava/lang/Object;Ljava/lang/Object;Ljava/lang/Object;)Ljava/lang/Object;
    //   570: aload_2
    //   571: invokestatic 1527	gnu/mapping/Values:writeValues	(Ljava/lang/Object;Lgnu/lists/Consumer;)V
    //   574: aload_0
    //   575: aconst_null
    //   576: putfield 1554	appinventor/ai_prafulmathur95/whereismycar/Screen1:HorizontalArrangement2	Lcom/google/appinventor/components/runtime/HorizontalArrangement;
    //   579: getstatic 1523	com/google/youngandroid/runtime:$Stthis$Mnis$Mnthe$Mnrepl$St	Ljava/lang/Object;
    //   582: getstatic 1316	java/lang/Boolean:FALSE	Ljava/lang/Boolean;
    //   585: if_acmpeq +1049 -> 1634
    //   588: getstatic 864	appinventor/ai_prafulmathur95/whereismycar/Screen1:Lit0	Lgnu/mapping/SimpleSymbol;
    //   591: getstatic 651	appinventor/ai_prafulmathur95/whereismycar/Screen1:Lit71	Lgnu/lists/FString;
    //   594: getstatic 649	appinventor/ai_prafulmathur95/whereismycar/Screen1:Lit72	Lgnu/mapping/SimpleSymbol;
    //   597: getstatic 1316	java/lang/Boolean:FALSE	Ljava/lang/Boolean;
    //   600: invokestatic 1540	com/google/youngandroid/runtime:addComponentWithinRepl	(Ljava/lang/Object;Ljava/lang/Object;Ljava/lang/Object;Ljava/lang/Object;)Ljava/lang/Object;
    //   603: aload_2
    //   604: invokestatic 1527	gnu/mapping/Values:writeValues	(Ljava/lang/Object;Lgnu/lists/Consumer;)V
    //   607: aload_0
    //   608: aconst_null
    //   609: putfield 1556	appinventor/ai_prafulmathur95/whereismycar/Screen1:Label4	Lcom/google/appinventor/components/runtime/Label;
    //   612: getstatic 1523	com/google/youngandroid/runtime:$Stthis$Mnis$Mnthe$Mnrepl$St	Ljava/lang/Object;
    //   615: getstatic 1316	java/lang/Boolean:FALSE	Ljava/lang/Boolean;
    //   618: if_acmpeq +1035 -> 1653
    //   621: getstatic 649	appinventor/ai_prafulmathur95/whereismycar/Screen1:Lit72	Lgnu/mapping/SimpleSymbol;
    //   624: getstatic 644	appinventor/ai_prafulmathur95/whereismycar/Screen1:Lit74	Lgnu/lists/FString;
    //   627: getstatic 642	appinventor/ai_prafulmathur95/whereismycar/Screen1:Lit75	Lgnu/mapping/SimpleSymbol;
    //   630: getstatic 959	appinventor/ai_prafulmathur95/whereismycar/Screen1:lambda$Fn16	Lgnu/expr/ModuleMethod;
    //   633: invokestatic 1540	com/google/youngandroid/runtime:addComponentWithinRepl	(Ljava/lang/Object;Ljava/lang/Object;Ljava/lang/Object;Ljava/lang/Object;)Ljava/lang/Object;
    //   636: aload_2
    //   637: invokestatic 1527	gnu/mapping/Values:writeValues	(Ljava/lang/Object;Lgnu/lists/Consumer;)V
    //   640: aload_0
    //   641: aconst_null
    //   642: putfield 1558	appinventor/ai_prafulmathur95/whereismycar/Screen1:currentlatlabel	Lcom/google/appinventor/components/runtime/Label;
    //   645: getstatic 1523	com/google/youngandroid/runtime:$Stthis$Mnis$Mnthe$Mnrepl$St	Ljava/lang/Object;
    //   648: getstatic 1316	java/lang/Boolean:FALSE	Ljava/lang/Boolean;
    //   651: if_acmpeq +1021 -> 1672
    //   654: getstatic 649	appinventor/ai_prafulmathur95/whereismycar/Screen1:Lit72	Lgnu/mapping/SimpleSymbol;
    //   657: getstatic 635	appinventor/ai_prafulmathur95/whereismycar/Screen1:Lit78	Lgnu/lists/FString;
    //   660: getstatic 633	appinventor/ai_prafulmathur95/whereismycar/Screen1:Lit79	Lgnu/mapping/SimpleSymbol;
    //   663: getstatic 963	appinventor/ai_prafulmathur95/whereismycar/Screen1:lambda$Fn18	Lgnu/expr/ModuleMethod;
    //   666: invokestatic 1540	com/google/youngandroid/runtime:addComponentWithinRepl	(Ljava/lang/Object;Ljava/lang/Object;Ljava/lang/Object;Ljava/lang/Object;)Ljava/lang/Object;
    //   669: aload_2
    //   670: invokestatic 1527	gnu/mapping/Values:writeValues	(Ljava/lang/Object;Lgnu/lists/Consumer;)V
    //   673: aload_0
    //   674: aconst_null
    //   675: putfield 1560	appinventor/ai_prafulmathur95/whereismycar/Screen1:Label6	Lcom/google/appinventor/components/runtime/Label;
    //   678: getstatic 1523	com/google/youngandroid/runtime:$Stthis$Mnis$Mnthe$Mnrepl$St	Ljava/lang/Object;
    //   681: getstatic 1316	java/lang/Boolean:FALSE	Ljava/lang/Boolean;
    //   684: if_acmpeq +1007 -> 1691
    //   687: getstatic 649	appinventor/ai_prafulmathur95/whereismycar/Screen1:Lit72	Lgnu/mapping/SimpleSymbol;
    //   690: getstatic 626	appinventor/ai_prafulmathur95/whereismycar/Screen1:Lit82	Lgnu/lists/FString;
    //   693: getstatic 624	appinventor/ai_prafulmathur95/whereismycar/Screen1:Lit83	Lgnu/mapping/SimpleSymbol;
    //   696: getstatic 967	appinventor/ai_prafulmathur95/whereismycar/Screen1:lambda$Fn20	Lgnu/expr/ModuleMethod;
    //   699: invokestatic 1540	com/google/youngandroid/runtime:addComponentWithinRepl	(Ljava/lang/Object;Ljava/lang/Object;Ljava/lang/Object;Ljava/lang/Object;)Ljava/lang/Object;
    //   702: aload_2
    //   703: invokestatic 1527	gnu/mapping/Values:writeValues	(Ljava/lang/Object;Lgnu/lists/Consumer;)V
    //   706: aload_0
    //   707: aconst_null
    //   708: putfield 1562	appinventor/ai_prafulmathur95/whereismycar/Screen1:currentlongLabel	Lcom/google/appinventor/components/runtime/Label;
    //   711: getstatic 1523	com/google/youngandroid/runtime:$Stthis$Mnis$Mnthe$Mnrepl$St	Ljava/lang/Object;
    //   714: getstatic 1316	java/lang/Boolean:FALSE	Ljava/lang/Boolean;
    //   717: if_acmpeq +993 -> 1710
    //   720: getstatic 649	appinventor/ai_prafulmathur95/whereismycar/Screen1:Lit72	Lgnu/mapping/SimpleSymbol;
    //   723: getstatic 617	appinventor/ai_prafulmathur95/whereismycar/Screen1:Lit86	Lgnu/lists/FString;
    //   726: getstatic 615	appinventor/ai_prafulmathur95/whereismycar/Screen1:Lit87	Lgnu/mapping/SimpleSymbol;
    //   729: getstatic 971	appinventor/ai_prafulmathur95/whereismycar/Screen1:lambda$Fn22	Lgnu/expr/ModuleMethod;
    //   732: invokestatic 1540	com/google/youngandroid/runtime:addComponentWithinRepl	(Ljava/lang/Object;Ljava/lang/Object;Ljava/lang/Object;Ljava/lang/Object;)Ljava/lang/Object;
    //   735: aload_2
    //   736: invokestatic 1527	gnu/mapping/Values:writeValues	(Ljava/lang/Object;Lgnu/lists/Consumer;)V
    //   739: aload_0
    //   740: aconst_null
    //   741: putfield 1564	appinventor/ai_prafulmathur95/whereismycar/Screen1:HorizontalArrangement6	Lcom/google/appinventor/components/runtime/HorizontalArrangement;
    //   744: getstatic 1523	com/google/youngandroid/runtime:$Stthis$Mnis$Mnthe$Mnrepl$St	Ljava/lang/Object;
    //   747: getstatic 1316	java/lang/Boolean:FALSE	Ljava/lang/Boolean;
    //   750: if_acmpeq +979 -> 1729
    //   753: getstatic 864	appinventor/ai_prafulmathur95/whereismycar/Screen1:Lit0	Lgnu/mapping/SimpleSymbol;
    //   756: getstatic 608	appinventor/ai_prafulmathur95/whereismycar/Screen1:Lit90	Lgnu/lists/FString;
    //   759: getstatic 606	appinventor/ai_prafulmathur95/whereismycar/Screen1:Lit91	Lgnu/mapping/SimpleSymbol;
    //   762: getstatic 1316	java/lang/Boolean:FALSE	Ljava/lang/Boolean;
    //   765: invokestatic 1540	com/google/youngandroid/runtime:addComponentWithinRepl	(Ljava/lang/Object;Ljava/lang/Object;Ljava/lang/Object;Ljava/lang/Object;)Ljava/lang/Object;
    //   768: aload_2
    //   769: invokestatic 1527	gnu/mapping/Values:writeValues	(Ljava/lang/Object;Lgnu/lists/Consumer;)V
    //   772: aload_0
    //   773: aconst_null
    //   774: putfield 1566	appinventor/ai_prafulmathur95/whereismycar/Screen1:RememberButton	Lcom/google/appinventor/components/runtime/Button;
    //   777: getstatic 1523	com/google/youngandroid/runtime:$Stthis$Mnis$Mnthe$Mnrepl$St	Ljava/lang/Object;
    //   780: getstatic 1316	java/lang/Boolean:FALSE	Ljava/lang/Boolean;
    //   783: if_acmpeq +965 -> 1748
    //   786: getstatic 606	appinventor/ai_prafulmathur95/whereismycar/Screen1:Lit91	Lgnu/mapping/SimpleSymbol;
    //   789: getstatic 601	appinventor/ai_prafulmathur95/whereismycar/Screen1:Lit93	Lgnu/lists/FString;
    //   792: getstatic 599	appinventor/ai_prafulmathur95/whereismycar/Screen1:Lit94	Lgnu/mapping/SimpleSymbol;
    //   795: getstatic 975	appinventor/ai_prafulmathur95/whereismycar/Screen1:lambda$Fn24	Lgnu/expr/ModuleMethod;
    //   798: invokestatic 1540	com/google/youngandroid/runtime:addComponentWithinRepl	(Ljava/lang/Object;Ljava/lang/Object;Ljava/lang/Object;Ljava/lang/Object;)Ljava/lang/Object;
    //   801: aload_2
    //   802: invokestatic 1527	gnu/mapping/Values:writeValues	(Ljava/lang/Object;Lgnu/lists/Consumer;)V
    //   805: getstatic 1523	com/google/youngandroid/runtime:$Stthis$Mnis$Mnthe$Mnrepl$St	Ljava/lang/Object;
    //   808: getstatic 1316	java/lang/Boolean:FALSE	Ljava/lang/Boolean;
    //   811: if_acmpeq +956 -> 1767
    //   814: getstatic 556	appinventor/ai_prafulmathur95/whereismycar/Screen1:Lit105	Lgnu/mapping/SimpleSymbol;
    //   817: aload_0
    //   818: getfield 979	appinventor/ai_prafulmathur95/whereismycar/Screen1:RememberButton$Click	Lgnu/expr/ModuleMethod;
    //   821: invokestatic 1530	com/google/youngandroid/runtime:addToCurrentFormEnvironment	(Lgnu/mapping/Symbol;Ljava/lang/Object;)Ljava/lang/Object;
    //   824: pop
    //   825: getstatic 1523	com/google/youngandroid/runtime:$Stthis$Mnis$Mnthe$Mnrepl$St	Ljava/lang/Object;
    //   828: getstatic 1316	java/lang/Boolean:FALSE	Ljava/lang/Boolean;
    //   831: if_acmpeq +950 -> 1781
    //   834: getstatic 1533	com/google/youngandroid/runtime:$Stthis$Mnform$St	Ljava/lang/Object;
    //   837: checkcast 1535	com/google/appinventor/components/runtime/HandlesEventDispatching
    //   840: ldc_w 597
    //   843: ldc_w 551
    //   846: invokestatic 1270	com/google/appinventor/components/runtime/EventDispatcher:registerEventForDelegation	(Lcom/google/appinventor/components/runtime/HandlesEventDispatching;Ljava/lang/String;Ljava/lang/String;)V
    //   849: aload_0
    //   850: aconst_null
    //   851: putfield 1568	appinventor/ai_prafulmathur95/whereismycar/Screen1:Label8	Lcom/google/appinventor/components/runtime/Label;
    //   854: getstatic 1523	com/google/youngandroid/runtime:$Stthis$Mnis$Mnthe$Mnrepl$St	Ljava/lang/Object;
    //   857: getstatic 1316	java/lang/Boolean:FALSE	Ljava/lang/Boolean;
    //   860: if_acmpeq +934 -> 1794
    //   863: getstatic 864	appinventor/ai_prafulmathur95/whereismycar/Screen1:Lit0	Lgnu/mapping/SimpleSymbol;
    //   866: getstatic 549	appinventor/ai_prafulmathur95/whereismycar/Screen1:Lit107	Lgnu/lists/FString;
    //   869: getstatic 547	appinventor/ai_prafulmathur95/whereismycar/Screen1:Lit108	Lgnu/mapping/SimpleSymbol;
    //   872: getstatic 981	appinventor/ai_prafulmathur95/whereismycar/Screen1:lambda$Fn26	Lgnu/expr/ModuleMethod;
    //   875: invokestatic 1540	com/google/youngandroid/runtime:addComponentWithinRepl	(Ljava/lang/Object;Ljava/lang/Object;Ljava/lang/Object;Ljava/lang/Object;)Ljava/lang/Object;
    //   878: aload_2
    //   879: invokestatic 1527	gnu/mapping/Values:writeValues	(Ljava/lang/Object;Lgnu/lists/Consumer;)V
    //   882: aload_0
    //   883: aconst_null
    //   884: putfield 1570	appinventor/ai_prafulmathur95/whereismycar/Screen1:HorizontalArrangement3	Lcom/google/appinventor/components/runtime/HorizontalArrangement;
    //   887: getstatic 1523	com/google/youngandroid/runtime:$Stthis$Mnis$Mnthe$Mnrepl$St	Ljava/lang/Object;
    //   890: getstatic 1316	java/lang/Boolean:FALSE	Ljava/lang/Boolean;
    //   893: if_acmpeq +920 -> 1813
    //   896: getstatic 864	appinventor/ai_prafulmathur95/whereismycar/Screen1:Lit0	Lgnu/mapping/SimpleSymbol;
    //   899: getstatic 540	appinventor/ai_prafulmathur95/whereismycar/Screen1:Lit111	Lgnu/lists/FString;
    //   902: getstatic 538	appinventor/ai_prafulmathur95/whereismycar/Screen1:Lit112	Lgnu/mapping/SimpleSymbol;
    //   905: getstatic 1316	java/lang/Boolean:FALSE	Ljava/lang/Boolean;
    //   908: invokestatic 1540	com/google/youngandroid/runtime:addComponentWithinRepl	(Ljava/lang/Object;Ljava/lang/Object;Ljava/lang/Object;Ljava/lang/Object;)Ljava/lang/Object;
    //   911: aload_2
    //   912: invokestatic 1527	gnu/mapping/Values:writeValues	(Ljava/lang/Object;Lgnu/lists/Consumer;)V
    //   915: aload_0
    //   916: aconst_null
    //   917: putfield 1572	appinventor/ai_prafulmathur95/whereismycar/Screen1:Label9	Lcom/google/appinventor/components/runtime/Label;
    //   920: getstatic 1523	com/google/youngandroid/runtime:$Stthis$Mnis$Mnthe$Mnrepl$St	Ljava/lang/Object;
    //   923: getstatic 1316	java/lang/Boolean:FALSE	Ljava/lang/Boolean;
    //   926: if_acmpeq +906 -> 1832
    //   929: getstatic 538	appinventor/ai_prafulmathur95/whereismycar/Screen1:Lit112	Lgnu/mapping/SimpleSymbol;
    //   932: getstatic 533	appinventor/ai_prafulmathur95/whereismycar/Screen1:Lit114	Lgnu/lists/FString;
    //   935: getstatic 531	appinventor/ai_prafulmathur95/whereismycar/Screen1:Lit115	Lgnu/mapping/SimpleSymbol;
    //   938: getstatic 985	appinventor/ai_prafulmathur95/whereismycar/Screen1:lambda$Fn28	Lgnu/expr/ModuleMethod;
    //   941: invokestatic 1540	com/google/youngandroid/runtime:addComponentWithinRepl	(Ljava/lang/Object;Ljava/lang/Object;Ljava/lang/Object;Ljava/lang/Object;)Ljava/lang/Object;
    //   944: aload_2
    //   945: invokestatic 1527	gnu/mapping/Values:writeValues	(Ljava/lang/Object;Lgnu/lists/Consumer;)V
    //   948: aload_0
    //   949: aconst_null
    //   950: putfield 1574	appinventor/ai_prafulmathur95/whereismycar/Screen1:rememberedaddressdatalabel	Lcom/google/appinventor/components/runtime/Label;
    //   953: getstatic 1523	com/google/youngandroid/runtime:$Stthis$Mnis$Mnthe$Mnrepl$St	Ljava/lang/Object;
    //   956: getstatic 1316	java/lang/Boolean:FALSE	Ljava/lang/Boolean;
    //   959: if_acmpeq +892 -> 1851
    //   962: getstatic 538	appinventor/ai_prafulmathur95/whereismycar/Screen1:Lit112	Lgnu/mapping/SimpleSymbol;
    //   965: getstatic 524	appinventor/ai_prafulmathur95/whereismycar/Screen1:Lit118	Lgnu/lists/FString;
    //   968: getstatic 779	appinventor/ai_prafulmathur95/whereismycar/Screen1:Lit24	Lgnu/mapping/SimpleSymbol;
    //   971: getstatic 989	appinventor/ai_prafulmathur95/whereismycar/Screen1:lambda$Fn30	Lgnu/expr/ModuleMethod;
    //   974: invokestatic 1540	com/google/youngandroid/runtime:addComponentWithinRepl	(Ljava/lang/Object;Ljava/lang/Object;Ljava/lang/Object;Ljava/lang/Object;)Ljava/lang/Object;
    //   977: aload_2
    //   978: invokestatic 1527	gnu/mapping/Values:writeValues	(Ljava/lang/Object;Lgnu/lists/Consumer;)V
    //   981: aload_0
    //   982: aconst_null
    //   983: putfield 1576	appinventor/ai_prafulmathur95/whereismycar/Screen1:HorizontalArrangement4	Lcom/google/appinventor/components/runtime/HorizontalArrangement;
    //   986: getstatic 1523	com/google/youngandroid/runtime:$Stthis$Mnis$Mnthe$Mnrepl$St	Ljava/lang/Object;
    //   989: getstatic 1316	java/lang/Boolean:FALSE	Ljava/lang/Boolean;
    //   992: if_acmpeq +878 -> 1870
    //   995: getstatic 864	appinventor/ai_prafulmathur95/whereismycar/Screen1:Lit0	Lgnu/mapping/SimpleSymbol;
    //   998: getstatic 518	appinventor/ai_prafulmathur95/whereismycar/Screen1:Lit121	Lgnu/lists/FString;
    //   1001: getstatic 516	appinventor/ai_prafulmathur95/whereismycar/Screen1:Lit122	Lgnu/mapping/SimpleSymbol;
    //   1004: getstatic 1316	java/lang/Boolean:FALSE	Ljava/lang/Boolean;
    //   1007: invokestatic 1540	com/google/youngandroid/runtime:addComponentWithinRepl	(Ljava/lang/Object;Ljava/lang/Object;Ljava/lang/Object;Ljava/lang/Object;)Ljava/lang/Object;
    //   1010: aload_2
    //   1011: invokestatic 1527	gnu/mapping/Values:writeValues	(Ljava/lang/Object;Lgnu/lists/Consumer;)V
    //   1014: aload_0
    //   1015: aconst_null
    //   1016: putfield 1578	appinventor/ai_prafulmathur95/whereismycar/Screen1:Label11	Lcom/google/appinventor/components/runtime/Label;
    //   1019: getstatic 1523	com/google/youngandroid/runtime:$Stthis$Mnis$Mnthe$Mnrepl$St	Ljava/lang/Object;
    //   1022: getstatic 1316	java/lang/Boolean:FALSE	Ljava/lang/Boolean;
    //   1025: if_acmpeq +864 -> 1889
    //   1028: getstatic 516	appinventor/ai_prafulmathur95/whereismycar/Screen1:Lit122	Lgnu/mapping/SimpleSymbol;
    //   1031: getstatic 509	appinventor/ai_prafulmathur95/whereismycar/Screen1:Lit124	Lgnu/lists/FString;
    //   1034: getstatic 507	appinventor/ai_prafulmathur95/whereismycar/Screen1:Lit125	Lgnu/mapping/SimpleSymbol;
    //   1037: getstatic 993	appinventor/ai_prafulmathur95/whereismycar/Screen1:lambda$Fn32	Lgnu/expr/ModuleMethod;
    //   1040: invokestatic 1540	com/google/youngandroid/runtime:addComponentWithinRepl	(Ljava/lang/Object;Ljava/lang/Object;Ljava/lang/Object;Ljava/lang/Object;)Ljava/lang/Object;
    //   1043: aload_2
    //   1044: invokestatic 1527	gnu/mapping/Values:writeValues	(Ljava/lang/Object;Lgnu/lists/Consumer;)V
    //   1047: aload_0
    //   1048: aconst_null
    //   1049: putfield 1580	appinventor/ai_prafulmathur95/whereismycar/Screen1:rememberedlatLabel	Lcom/google/appinventor/components/runtime/Label;
    //   1052: getstatic 1523	com/google/youngandroid/runtime:$Stthis$Mnis$Mnthe$Mnrepl$St	Ljava/lang/Object;
    //   1055: getstatic 1316	java/lang/Boolean:FALSE	Ljava/lang/Boolean;
    //   1058: if_acmpeq +850 -> 1908
    //   1061: getstatic 516	appinventor/ai_prafulmathur95/whereismycar/Screen1:Lit122	Lgnu/mapping/SimpleSymbol;
    //   1064: getstatic 500	appinventor/ai_prafulmathur95/whereismycar/Screen1:Lit128	Lgnu/lists/FString;
    //   1067: getstatic 772	appinventor/ai_prafulmathur95/whereismycar/Screen1:Lit26	Lgnu/mapping/SimpleSymbol;
    //   1070: getstatic 997	appinventor/ai_prafulmathur95/whereismycar/Screen1:lambda$Fn34	Lgnu/expr/ModuleMethod;
    //   1073: invokestatic 1540	com/google/youngandroid/runtime:addComponentWithinRepl	(Ljava/lang/Object;Ljava/lang/Object;Ljava/lang/Object;Ljava/lang/Object;)Ljava/lang/Object;
    //   1076: aload_2
    //   1077: invokestatic 1527	gnu/mapping/Values:writeValues	(Ljava/lang/Object;Lgnu/lists/Consumer;)V
    //   1080: aload_0
    //   1081: aconst_null
    //   1082: putfield 1582	appinventor/ai_prafulmathur95/whereismycar/Screen1:Label13	Lcom/google/appinventor/components/runtime/Label;
    //   1085: getstatic 1523	com/google/youngandroid/runtime:$Stthis$Mnis$Mnthe$Mnrepl$St	Ljava/lang/Object;
    //   1088: getstatic 1316	java/lang/Boolean:FALSE	Ljava/lang/Boolean;
    //   1091: if_acmpeq +836 -> 1927
    //   1094: getstatic 516	appinventor/ai_prafulmathur95/whereismycar/Screen1:Lit122	Lgnu/mapping/SimpleSymbol;
    //   1097: getstatic 494	appinventor/ai_prafulmathur95/whereismycar/Screen1:Lit131	Lgnu/lists/FString;
    //   1100: getstatic 492	appinventor/ai_prafulmathur95/whereismycar/Screen1:Lit132	Lgnu/mapping/SimpleSymbol;
    //   1103: getstatic 1001	appinventor/ai_prafulmathur95/whereismycar/Screen1:lambda$Fn36	Lgnu/expr/ModuleMethod;
    //   1106: invokestatic 1540	com/google/youngandroid/runtime:addComponentWithinRepl	(Ljava/lang/Object;Ljava/lang/Object;Ljava/lang/Object;Ljava/lang/Object;)Ljava/lang/Object;
    //   1109: aload_2
    //   1110: invokestatic 1527	gnu/mapping/Values:writeValues	(Ljava/lang/Object;Lgnu/lists/Consumer;)V
    //   1113: aload_0
    //   1114: aconst_null
    //   1115: putfield 1584	appinventor/ai_prafulmathur95/whereismycar/Screen1:rememberedLongLabel	Lcom/google/appinventor/components/runtime/Label;
    //   1118: getstatic 1523	com/google/youngandroid/runtime:$Stthis$Mnis$Mnthe$Mnrepl$St	Ljava/lang/Object;
    //   1121: getstatic 1316	java/lang/Boolean:FALSE	Ljava/lang/Boolean;
    //   1124: if_acmpeq +822 -> 1946
    //   1127: getstatic 516	appinventor/ai_prafulmathur95/whereismycar/Screen1:Lit122	Lgnu/mapping/SimpleSymbol;
    //   1130: getstatic 485	appinventor/ai_prafulmathur95/whereismycar/Screen1:Lit135	Lgnu/lists/FString;
    //   1133: getstatic 762	appinventor/ai_prafulmathur95/whereismycar/Screen1:Lit29	Lgnu/mapping/SimpleSymbol;
    //   1136: getstatic 1005	appinventor/ai_prafulmathur95/whereismycar/Screen1:lambda$Fn38	Lgnu/expr/ModuleMethod;
    //   1139: invokestatic 1540	com/google/youngandroid/runtime:addComponentWithinRepl	(Ljava/lang/Object;Ljava/lang/Object;Ljava/lang/Object;Ljava/lang/Object;)Ljava/lang/Object;
    //   1142: aload_2
    //   1143: invokestatic 1527	gnu/mapping/Values:writeValues	(Ljava/lang/Object;Lgnu/lists/Consumer;)V
    //   1146: aload_0
    //   1147: aconst_null
    //   1148: putfield 1586	appinventor/ai_prafulmathur95/whereismycar/Screen1:directionbutton	Lcom/google/appinventor/components/runtime/Button;
    //   1151: getstatic 1523	com/google/youngandroid/runtime:$Stthis$Mnis$Mnthe$Mnrepl$St	Ljava/lang/Object;
    //   1154: getstatic 1316	java/lang/Boolean:FALSE	Ljava/lang/Boolean;
    //   1157: if_acmpeq +808 -> 1965
    //   1160: getstatic 864	appinventor/ai_prafulmathur95/whereismycar/Screen1:Lit0	Lgnu/mapping/SimpleSymbol;
    //   1163: getstatic 472	appinventor/ai_prafulmathur95/whereismycar/Screen1:Lit138	Lgnu/lists/FString;
    //   1166: getstatic 752	appinventor/ai_prafulmathur95/whereismycar/Screen1:Lit32	Lgnu/mapping/SimpleSymbol;
    //   1169: getstatic 1009	appinventor/ai_prafulmathur95/whereismycar/Screen1:lambda$Fn40	Lgnu/expr/ModuleMethod;
    //   1172: invokestatic 1540	com/google/youngandroid/runtime:addComponentWithinRepl	(Ljava/lang/Object;Ljava/lang/Object;Ljava/lang/Object;Ljava/lang/Object;)Ljava/lang/Object;
    //   1175: aload_2
    //   1176: invokestatic 1527	gnu/mapping/Values:writeValues	(Ljava/lang/Object;Lgnu/lists/Consumer;)V
    //   1179: getstatic 1523	com/google/youngandroid/runtime:$Stthis$Mnis$Mnthe$Mnrepl$St	Ljava/lang/Object;
    //   1182: getstatic 1316	java/lang/Boolean:FALSE	Ljava/lang/Boolean;
    //   1185: if_acmpeq +799 -> 1984
    //   1188: getstatic 414	appinventor/ai_prafulmathur95/whereismycar/Screen1:Lit147	Lgnu/mapping/SimpleSymbol;
    //   1191: aload_0
    //   1192: getfield 1017	appinventor/ai_prafulmathur95/whereismycar/Screen1:directionbutton$Click	Lgnu/expr/ModuleMethod;
    //   1195: invokestatic 1530	com/google/youngandroid/runtime:addToCurrentFormEnvironment	(Lgnu/mapping/Symbol;Ljava/lang/Object;)Ljava/lang/Object;
    //   1198: pop
    //   1199: getstatic 1523	com/google/youngandroid/runtime:$Stthis$Mnis$Mnthe$Mnrepl$St	Ljava/lang/Object;
    //   1202: getstatic 1316	java/lang/Boolean:FALSE	Ljava/lang/Boolean;
    //   1205: if_acmpeq +793 -> 1998
    //   1208: getstatic 1533	com/google/youngandroid/runtime:$Stthis$Mnform$St	Ljava/lang/Object;
    //   1211: checkcast 1535	com/google/appinventor/components/runtime/HandlesEventDispatching
    //   1214: ldc_w 750
    //   1217: ldc_w 551
    //   1220: invokestatic 1270	com/google/appinventor/components/runtime/EventDispatcher:registerEventForDelegation	(Lcom/google/appinventor/components/runtime/HandlesEventDispatching;Ljava/lang/String;Ljava/lang/String;)V
    //   1223: aload_0
    //   1224: aconst_null
    //   1225: putfield 1588	appinventor/ai_prafulmathur95/whereismycar/Screen1:LocationSensor1	Lcom/google/appinventor/components/runtime/LocationSensor;
    //   1228: getstatic 1523	com/google/youngandroid/runtime:$Stthis$Mnis$Mnthe$Mnrepl$St	Ljava/lang/Object;
    //   1231: getstatic 1316	java/lang/Boolean:FALSE	Ljava/lang/Boolean;
    //   1234: if_acmpeq +777 -> 2011
    //   1237: getstatic 864	appinventor/ai_prafulmathur95/whereismycar/Screen1:Lit0	Lgnu/mapping/SimpleSymbol;
    //   1240: getstatic 411	appinventor/ai_prafulmathur95/whereismycar/Screen1:Lit148	Lgnu/lists/FString;
    //   1243: getstatic 810	appinventor/ai_prafulmathur95/whereismycar/Screen1:Lit16	Lgnu/mapping/SimpleSymbol;
    //   1246: getstatic 1316	java/lang/Boolean:FALSE	Ljava/lang/Boolean;
    //   1249: invokestatic 1540	com/google/youngandroid/runtime:addComponentWithinRepl	(Ljava/lang/Object;Ljava/lang/Object;Ljava/lang/Object;Ljava/lang/Object;)Ljava/lang/Object;
    //   1252: aload_2
    //   1253: invokestatic 1527	gnu/mapping/Values:writeValues	(Ljava/lang/Object;Lgnu/lists/Consumer;)V
    //   1256: getstatic 1523	com/google/youngandroid/runtime:$Stthis$Mnis$Mnthe$Mnrepl$St	Ljava/lang/Object;
    //   1259: getstatic 1316	java/lang/Boolean:FALSE	Ljava/lang/Boolean;
    //   1262: if_acmpeq +768 -> 2030
    //   1265: getstatic 405	appinventor/ai_prafulmathur95/whereismycar/Screen1:Lit150	Lgnu/mapping/SimpleSymbol;
    //   1268: aload_0
    //   1269: getfield 1019	appinventor/ai_prafulmathur95/whereismycar/Screen1:LocationSensor1$LocationChanged	Lgnu/expr/ModuleMethod;
    //   1272: invokestatic 1530	com/google/youngandroid/runtime:addToCurrentFormEnvironment	(Lgnu/mapping/Symbol;Ljava/lang/Object;)Ljava/lang/Object;
    //   1275: pop
    //   1276: getstatic 1523	com/google/youngandroid/runtime:$Stthis$Mnis$Mnthe$Mnrepl$St	Ljava/lang/Object;
    //   1279: getstatic 1316	java/lang/Boolean:FALSE	Ljava/lang/Boolean;
    //   1282: if_acmpeq +762 -> 2044
    //   1285: getstatic 1533	com/google/youngandroid/runtime:$Stthis$Mnform$St	Ljava/lang/Object;
    //   1288: checkcast 1535	com/google/appinventor/components/runtime/HandlesEventDispatching
    //   1291: ldc_w 808
    //   1294: ldc_w 400
    //   1297: invokestatic 1270	com/google/appinventor/components/runtime/EventDispatcher:registerEventForDelegation	(Lcom/google/appinventor/components/runtime/HandlesEventDispatching;Ljava/lang/String;Ljava/lang/String;)V
    //   1300: aload_0
    //   1301: aconst_null
    //   1302: putfield 1590	appinventor/ai_prafulmathur95/whereismycar/Screen1:ActivityStarter1	Lcom/google/appinventor/components/runtime/ActivityStarter;
    //   1305: getstatic 1523	com/google/youngandroid/runtime:$Stthis$Mnis$Mnthe$Mnrepl$St	Ljava/lang/Object;
    //   1308: getstatic 1316	java/lang/Boolean:FALSE	Ljava/lang/Boolean;
    //   1311: if_acmpeq +746 -> 2057
    //   1314: getstatic 864	appinventor/ai_prafulmathur95/whereismycar/Screen1:Lit0	Lgnu/mapping/SimpleSymbol;
    //   1317: getstatic 398	appinventor/ai_prafulmathur95/whereismycar/Screen1:Lit152	Lgnu/lists/FString;
    //   1320: getstatic 458	appinventor/ai_prafulmathur95/whereismycar/Screen1:Lit142	Lgnu/mapping/SimpleSymbol;
    //   1323: getstatic 1021	appinventor/ai_prafulmathur95/whereismycar/Screen1:lambda$Fn44	Lgnu/expr/ModuleMethod;
    //   1326: invokestatic 1540	com/google/youngandroid/runtime:addComponentWithinRepl	(Ljava/lang/Object;Ljava/lang/Object;Ljava/lang/Object;Ljava/lang/Object;)Ljava/lang/Object;
    //   1329: aload_2
    //   1330: invokestatic 1527	gnu/mapping/Values:writeValues	(Ljava/lang/Object;Lgnu/lists/Consumer;)V
    //   1333: aload_0
    //   1334: aconst_null
    //   1335: putfield 1592	appinventor/ai_prafulmathur95/whereismycar/Screen1:TinyDB1	Lcom/google/appinventor/components/runtime/TinyDB;
    //   1338: getstatic 1523	com/google/youngandroid/runtime:$Stthis$Mnis$Mnthe$Mnrepl$St	Ljava/lang/Object;
    //   1341: getstatic 1316	java/lang/Boolean:FALSE	Ljava/lang/Boolean;
    //   1344: if_acmpeq +732 -> 2076
    //   1347: getstatic 864	appinventor/ai_prafulmathur95/whereismycar/Screen1:Lit0	Lgnu/mapping/SimpleSymbol;
    //   1350: getstatic 380	appinventor/ai_prafulmathur95/whereismycar/Screen1:Lit157	Lgnu/lists/FString;
    //   1353: getstatic 803	appinventor/ai_prafulmathur95/whereismycar/Screen1:Lit18	Lgnu/mapping/SimpleSymbol;
    //   1356: getstatic 1316	java/lang/Boolean:FALSE	Ljava/lang/Boolean;
    //   1359: invokestatic 1540	com/google/youngandroid/runtime:addComponentWithinRepl	(Ljava/lang/Object;Ljava/lang/Object;Ljava/lang/Object;Ljava/lang/Object;)Ljava/lang/Object;
    //   1362: aload_2
    //   1363: invokestatic 1527	gnu/mapping/Values:writeValues	(Ljava/lang/Object;Lgnu/lists/Consumer;)V
    //   1366: aload_0
    //   1367: aconst_null
    //   1368: putfield 1594	appinventor/ai_prafulmathur95/whereismycar/Screen1:TinyDB2	Lcom/google/appinventor/components/runtime/TinyDB;
    //   1371: getstatic 1523	com/google/youngandroid/runtime:$Stthis$Mnis$Mnthe$Mnrepl$St	Ljava/lang/Object;
    //   1374: getstatic 1316	java/lang/Boolean:FALSE	Ljava/lang/Boolean;
    //   1377: if_acmpeq +718 -> 2095
    //   1380: getstatic 864	appinventor/ai_prafulmathur95/whereismycar/Screen1:Lit0	Lgnu/mapping/SimpleSymbol;
    //   1383: getstatic 376	appinventor/ai_prafulmathur95/whereismycar/Screen1:Lit159	Lgnu/lists/FString;
    //   1386: getstatic 769	appinventor/ai_prafulmathur95/whereismycar/Screen1:Lit27	Lgnu/mapping/SimpleSymbol;
    //   1389: getstatic 1316	java/lang/Boolean:FALSE	Ljava/lang/Boolean;
    //   1392: invokestatic 1540	com/google/youngandroid/runtime:addComponentWithinRepl	(Ljava/lang/Object;Ljava/lang/Object;Ljava/lang/Object;Ljava/lang/Object;)Ljava/lang/Object;
    //   1395: aload_2
    //   1396: invokestatic 1527	gnu/mapping/Values:writeValues	(Ljava/lang/Object;Lgnu/lists/Consumer;)V
    //   1399: aload_0
    //   1400: aconst_null
    //   1401: putfield 1596	appinventor/ai_prafulmathur95/whereismycar/Screen1:TinyDB3	Lcom/google/appinventor/components/runtime/TinyDB;
    //   1404: getstatic 1523	com/google/youngandroid/runtime:$Stthis$Mnis$Mnthe$Mnrepl$St	Ljava/lang/Object;
    //   1407: getstatic 1316	java/lang/Boolean:FALSE	Ljava/lang/Boolean;
    //   1410: if_acmpeq +704 -> 2114
    //   1413: getstatic 864	appinventor/ai_prafulmathur95/whereismycar/Screen1:Lit0	Lgnu/mapping/SimpleSymbol;
    //   1416: getstatic 372	appinventor/ai_prafulmathur95/whereismycar/Screen1:Lit161	Lgnu/lists/FString;
    //   1419: getstatic 759	appinventor/ai_prafulmathur95/whereismycar/Screen1:Lit30	Lgnu/mapping/SimpleSymbol;
    //   1422: getstatic 1316	java/lang/Boolean:FALSE	Ljava/lang/Boolean;
    //   1425: invokestatic 1540	com/google/youngandroid/runtime:addComponentWithinRepl	(Ljava/lang/Object;Ljava/lang/Object;Ljava/lang/Object;Ljava/lang/Object;)Ljava/lang/Object;
    //   1428: aload_2
    //   1429: invokestatic 1527	gnu/mapping/Values:writeValues	(Ljava/lang/Object;Lgnu/lists/Consumer;)V
    //   1432: invokestatic 1599	com/google/youngandroid/runtime:initRuntime	()V
    //   1435: return
    //   1436: aload_1
    //   1437: invokevirtual 1275	java/lang/Object:toString	()Ljava/lang/String;
    //   1440: astore_1
    //   1441: goto -1369 -> 72
    //   1444: aload_0
    //   1445: getstatic 853	appinventor/ai_prafulmathur95/whereismycar/Screen1:Lit3	Lgnu/mapping/SimpleSymbol;
    //   1448: getstatic 929	appinventor/ai_prafulmathur95/whereismycar/Screen1:lambda$Fn2	Lgnu/expr/ModuleMethod;
    //   1451: invokevirtual 1233	appinventor/ai_prafulmathur95/whereismycar/Screen1:addToGlobalVars	(Ljava/lang/Object;Ljava/lang/Object;)V
    //   1454: goto -1295 -> 159
    //   1457: aload_0
    //   1458: new 1601	kawa/lang/Promise
    //   1461: dup
    //   1462: getstatic 931	appinventor/ai_prafulmathur95/whereismycar/Screen1:lambda$Fn3	Lgnu/expr/ModuleMethod;
    //   1465: invokespecial 1604	kawa/lang/Promise:<init>	(Lgnu/mapping/Procedure;)V
    //   1468: invokevirtual 1606	appinventor/ai_prafulmathur95/whereismycar/Screen1:addToFormDoAfterCreation	(Ljava/lang/Object;)V
    //   1471: goto -1172 -> 299
    //   1474: aload_0
    //   1475: getstatic 749	appinventor/ai_prafulmathur95/whereismycar/Screen1:Lit33	Lgnu/mapping/SimpleSymbol;
    //   1478: aload_0
    //   1479: getfield 933	appinventor/ai_prafulmathur95/whereismycar/Screen1:Screen1$Initialize	Lgnu/expr/ModuleMethod;
    //   1482: invokevirtual 1228	appinventor/ai_prafulmathur95/whereismycar/Screen1:addToFormEnvironment	(Lgnu/mapping/Symbol;Ljava/lang/Object;)V
    //   1485: goto -1166 -> 319
    //   1488: aload_0
    //   1489: getstatic 864	appinventor/ai_prafulmathur95/whereismycar/Screen1:Lit0	Lgnu/mapping/SimpleSymbol;
    //   1492: getstatic 746	appinventor/ai_prafulmathur95/whereismycar/Screen1:Lit34	Lgnu/mapping/SimpleSymbol;
    //   1495: invokevirtual 1608	appinventor/ai_prafulmathur95/whereismycar/Screen1:addToEvents	(Ljava/lang/Object;Ljava/lang/Object;)V
    //   1498: goto -1155 -> 343
    //   1501: aload_0
    //   1502: getstatic 864	appinventor/ai_prafulmathur95/whereismycar/Screen1:Lit0	Lgnu/mapping/SimpleSymbol;
    //   1505: getstatic 725	appinventor/ai_prafulmathur95/whereismycar/Screen1:Lit41	Lgnu/lists/FString;
    //   1508: getstatic 740	appinventor/ai_prafulmathur95/whereismycar/Screen1:Lit36	Lgnu/mapping/SimpleSymbol;
    //   1511: getstatic 937	appinventor/ai_prafulmathur95/whereismycar/Screen1:lambda$Fn5	Lgnu/expr/ModuleMethod;
    //   1514: invokevirtual 1610	appinventor/ai_prafulmathur95/whereismycar/Screen1:addToComponents	(Ljava/lang/Object;Ljava/lang/Object;Ljava/lang/Object;Ljava/lang/Object;)V
    //   1517: goto -1141 -> 376
    //   1520: aload_0
    //   1521: getstatic 864	appinventor/ai_prafulmathur95/whereismycar/Screen1:Lit0	Lgnu/mapping/SimpleSymbol;
    //   1524: getstatic 718	appinventor/ai_prafulmathur95/whereismycar/Screen1:Lit44	Lgnu/lists/FString;
    //   1527: getstatic 721	appinventor/ai_prafulmathur95/whereismycar/Screen1:Lit43	Lgnu/mapping/SimpleSymbol;
    //   1530: getstatic 941	appinventor/ai_prafulmathur95/whereismycar/Screen1:lambda$Fn7	Lgnu/expr/ModuleMethod;
    //   1533: invokevirtual 1610	appinventor/ai_prafulmathur95/whereismycar/Screen1:addToComponents	(Ljava/lang/Object;Ljava/lang/Object;Ljava/lang/Object;Ljava/lang/Object;)V
    //   1536: goto -1127 -> 409
    //   1539: aload_0
    //   1540: getstatic 721	appinventor/ai_prafulmathur95/whereismycar/Screen1:Lit43	Lgnu/mapping/SimpleSymbol;
    //   1543: getstatic 709	appinventor/ai_prafulmathur95/whereismycar/Screen1:Lit48	Lgnu/lists/FString;
    //   1546: getstatic 714	appinventor/ai_prafulmathur95/whereismycar/Screen1:Lit46	Lgnu/mapping/SimpleSymbol;
    //   1549: getstatic 945	appinventor/ai_prafulmathur95/whereismycar/Screen1:lambda$Fn9	Lgnu/expr/ModuleMethod;
    //   1552: invokevirtual 1610	appinventor/ai_prafulmathur95/whereismycar/Screen1:addToComponents	(Ljava/lang/Object;Ljava/lang/Object;Ljava/lang/Object;Ljava/lang/Object;)V
    //   1555: goto -1113 -> 442
    //   1558: aload_0
    //   1559: getstatic 721	appinventor/ai_prafulmathur95/whereismycar/Screen1:Lit43	Lgnu/mapping/SimpleSymbol;
    //   1562: getstatic 682	appinventor/ai_prafulmathur95/whereismycar/Screen1:Lit57	Lgnu/lists/FString;
    //   1565: getstatic 703	appinventor/ai_prafulmathur95/whereismycar/Screen1:Lit50	Lgnu/mapping/SimpleSymbol;
    //   1568: getstatic 949	appinventor/ai_prafulmathur95/whereismycar/Screen1:lambda$Fn11	Lgnu/expr/ModuleMethod;
    //   1571: invokevirtual 1610	appinventor/ai_prafulmathur95/whereismycar/Screen1:addToComponents	(Ljava/lang/Object;Ljava/lang/Object;Ljava/lang/Object;Ljava/lang/Object;)V
    //   1574: goto -1099 -> 475
    //   1577: aload_0
    //   1578: getstatic 864	appinventor/ai_prafulmathur95/whereismycar/Screen1:Lit0	Lgnu/mapping/SimpleSymbol;
    //   1581: getstatic 675	appinventor/ai_prafulmathur95/whereismycar/Screen1:Lit60	Lgnu/lists/FString;
    //   1584: getstatic 678	appinventor/ai_prafulmathur95/whereismycar/Screen1:Lit59	Lgnu/mapping/SimpleSymbol;
    //   1587: getstatic 1316	java/lang/Boolean:FALSE	Ljava/lang/Boolean;
    //   1590: invokevirtual 1610	appinventor/ai_prafulmathur95/whereismycar/Screen1:addToComponents	(Ljava/lang/Object;Ljava/lang/Object;Ljava/lang/Object;Ljava/lang/Object;)V
    //   1593: goto -1085 -> 508
    //   1596: aload_0
    //   1597: getstatic 678	appinventor/ai_prafulmathur95/whereismycar/Screen1:Lit59	Lgnu/mapping/SimpleSymbol;
    //   1600: getstatic 664	appinventor/ai_prafulmathur95/whereismycar/Screen1:Lit65	Lgnu/lists/FString;
    //   1603: getstatic 671	appinventor/ai_prafulmathur95/whereismycar/Screen1:Lit62	Lgnu/mapping/SimpleSymbol;
    //   1606: getstatic 953	appinventor/ai_prafulmathur95/whereismycar/Screen1:lambda$Fn13	Lgnu/expr/ModuleMethod;
    //   1609: invokevirtual 1610	appinventor/ai_prafulmathur95/whereismycar/Screen1:addToComponents	(Ljava/lang/Object;Ljava/lang/Object;Ljava/lang/Object;Ljava/lang/Object;)V
    //   1612: goto -1071 -> 541
    //   1615: aload_0
    //   1616: getstatic 678	appinventor/ai_prafulmathur95/whereismycar/Screen1:Lit59	Lgnu/mapping/SimpleSymbol;
    //   1619: getstatic 653	appinventor/ai_prafulmathur95/whereismycar/Screen1:Lit70	Lgnu/lists/FString;
    //   1622: getstatic 660	appinventor/ai_prafulmathur95/whereismycar/Screen1:Lit67	Lgnu/mapping/SimpleSymbol;
    //   1625: getstatic 957	appinventor/ai_prafulmathur95/whereismycar/Screen1:lambda$Fn15	Lgnu/expr/ModuleMethod;
    //   1628: invokevirtual 1610	appinventor/ai_prafulmathur95/whereismycar/Screen1:addToComponents	(Ljava/lang/Object;Ljava/lang/Object;Ljava/lang/Object;Ljava/lang/Object;)V
    //   1631: goto -1057 -> 574
    //   1634: aload_0
    //   1635: getstatic 864	appinventor/ai_prafulmathur95/whereismycar/Screen1:Lit0	Lgnu/mapping/SimpleSymbol;
    //   1638: getstatic 646	appinventor/ai_prafulmathur95/whereismycar/Screen1:Lit73	Lgnu/lists/FString;
    //   1641: getstatic 649	appinventor/ai_prafulmathur95/whereismycar/Screen1:Lit72	Lgnu/mapping/SimpleSymbol;
    //   1644: getstatic 1316	java/lang/Boolean:FALSE	Ljava/lang/Boolean;
    //   1647: invokevirtual 1610	appinventor/ai_prafulmathur95/whereismycar/Screen1:addToComponents	(Ljava/lang/Object;Ljava/lang/Object;Ljava/lang/Object;Ljava/lang/Object;)V
    //   1650: goto -1043 -> 607
    //   1653: aload_0
    //   1654: getstatic 649	appinventor/ai_prafulmathur95/whereismycar/Screen1:Lit72	Lgnu/mapping/SimpleSymbol;
    //   1657: getstatic 637	appinventor/ai_prafulmathur95/whereismycar/Screen1:Lit77	Lgnu/lists/FString;
    //   1660: getstatic 642	appinventor/ai_prafulmathur95/whereismycar/Screen1:Lit75	Lgnu/mapping/SimpleSymbol;
    //   1663: getstatic 961	appinventor/ai_prafulmathur95/whereismycar/Screen1:lambda$Fn17	Lgnu/expr/ModuleMethod;
    //   1666: invokevirtual 1610	appinventor/ai_prafulmathur95/whereismycar/Screen1:addToComponents	(Ljava/lang/Object;Ljava/lang/Object;Ljava/lang/Object;Ljava/lang/Object;)V
    //   1669: goto -1029 -> 640
    //   1672: aload_0
    //   1673: getstatic 649	appinventor/ai_prafulmathur95/whereismycar/Screen1:Lit72	Lgnu/mapping/SimpleSymbol;
    //   1676: getstatic 628	appinventor/ai_prafulmathur95/whereismycar/Screen1:Lit81	Lgnu/lists/FString;
    //   1679: getstatic 633	appinventor/ai_prafulmathur95/whereismycar/Screen1:Lit79	Lgnu/mapping/SimpleSymbol;
    //   1682: getstatic 965	appinventor/ai_prafulmathur95/whereismycar/Screen1:lambda$Fn19	Lgnu/expr/ModuleMethod;
    //   1685: invokevirtual 1610	appinventor/ai_prafulmathur95/whereismycar/Screen1:addToComponents	(Ljava/lang/Object;Ljava/lang/Object;Ljava/lang/Object;Ljava/lang/Object;)V
    //   1688: goto -1015 -> 673
    //   1691: aload_0
    //   1692: getstatic 649	appinventor/ai_prafulmathur95/whereismycar/Screen1:Lit72	Lgnu/mapping/SimpleSymbol;
    //   1695: getstatic 619	appinventor/ai_prafulmathur95/whereismycar/Screen1:Lit85	Lgnu/lists/FString;
    //   1698: getstatic 624	appinventor/ai_prafulmathur95/whereismycar/Screen1:Lit83	Lgnu/mapping/SimpleSymbol;
    //   1701: getstatic 969	appinventor/ai_prafulmathur95/whereismycar/Screen1:lambda$Fn21	Lgnu/expr/ModuleMethod;
    //   1704: invokevirtual 1610	appinventor/ai_prafulmathur95/whereismycar/Screen1:addToComponents	(Ljava/lang/Object;Ljava/lang/Object;Ljava/lang/Object;Ljava/lang/Object;)V
    //   1707: goto -1001 -> 706
    //   1710: aload_0
    //   1711: getstatic 649	appinventor/ai_prafulmathur95/whereismycar/Screen1:Lit72	Lgnu/mapping/SimpleSymbol;
    //   1714: getstatic 610	appinventor/ai_prafulmathur95/whereismycar/Screen1:Lit89	Lgnu/lists/FString;
    //   1717: getstatic 615	appinventor/ai_prafulmathur95/whereismycar/Screen1:Lit87	Lgnu/mapping/SimpleSymbol;
    //   1720: getstatic 973	appinventor/ai_prafulmathur95/whereismycar/Screen1:lambda$Fn23	Lgnu/expr/ModuleMethod;
    //   1723: invokevirtual 1610	appinventor/ai_prafulmathur95/whereismycar/Screen1:addToComponents	(Ljava/lang/Object;Ljava/lang/Object;Ljava/lang/Object;Ljava/lang/Object;)V
    //   1726: goto -987 -> 739
    //   1729: aload_0
    //   1730: getstatic 864	appinventor/ai_prafulmathur95/whereismycar/Screen1:Lit0	Lgnu/mapping/SimpleSymbol;
    //   1733: getstatic 603	appinventor/ai_prafulmathur95/whereismycar/Screen1:Lit92	Lgnu/lists/FString;
    //   1736: getstatic 606	appinventor/ai_prafulmathur95/whereismycar/Screen1:Lit91	Lgnu/mapping/SimpleSymbol;
    //   1739: getstatic 1316	java/lang/Boolean:FALSE	Ljava/lang/Boolean;
    //   1742: invokevirtual 1610	appinventor/ai_prafulmathur95/whereismycar/Screen1:addToComponents	(Ljava/lang/Object;Ljava/lang/Object;Ljava/lang/Object;Ljava/lang/Object;)V
    //   1745: goto -973 -> 772
    //   1748: aload_0
    //   1749: getstatic 606	appinventor/ai_prafulmathur95/whereismycar/Screen1:Lit91	Lgnu/mapping/SimpleSymbol;
    //   1752: getstatic 586	appinventor/ai_prafulmathur95/whereismycar/Screen1:Lit97	Lgnu/lists/FString;
    //   1755: getstatic 599	appinventor/ai_prafulmathur95/whereismycar/Screen1:Lit94	Lgnu/mapping/SimpleSymbol;
    //   1758: getstatic 977	appinventor/ai_prafulmathur95/whereismycar/Screen1:lambda$Fn25	Lgnu/expr/ModuleMethod;
    //   1761: invokevirtual 1610	appinventor/ai_prafulmathur95/whereismycar/Screen1:addToComponents	(Ljava/lang/Object;Ljava/lang/Object;Ljava/lang/Object;Ljava/lang/Object;)V
    //   1764: goto -959 -> 805
    //   1767: aload_0
    //   1768: getstatic 556	appinventor/ai_prafulmathur95/whereismycar/Screen1:Lit105	Lgnu/mapping/SimpleSymbol;
    //   1771: aload_0
    //   1772: getfield 979	appinventor/ai_prafulmathur95/whereismycar/Screen1:RememberButton$Click	Lgnu/expr/ModuleMethod;
    //   1775: invokevirtual 1228	appinventor/ai_prafulmathur95/whereismycar/Screen1:addToFormEnvironment	(Lgnu/mapping/Symbol;Ljava/lang/Object;)V
    //   1778: goto -953 -> 825
    //   1781: aload_0
    //   1782: getstatic 599	appinventor/ai_prafulmathur95/whereismycar/Screen1:Lit94	Lgnu/mapping/SimpleSymbol;
    //   1785: getstatic 553	appinventor/ai_prafulmathur95/whereismycar/Screen1:Lit106	Lgnu/mapping/SimpleSymbol;
    //   1788: invokevirtual 1608	appinventor/ai_prafulmathur95/whereismycar/Screen1:addToEvents	(Ljava/lang/Object;Ljava/lang/Object;)V
    //   1791: goto -942 -> 849
    //   1794: aload_0
    //   1795: getstatic 864	appinventor/ai_prafulmathur95/whereismycar/Screen1:Lit0	Lgnu/mapping/SimpleSymbol;
    //   1798: getstatic 542	appinventor/ai_prafulmathur95/whereismycar/Screen1:Lit110	Lgnu/lists/FString;
    //   1801: getstatic 547	appinventor/ai_prafulmathur95/whereismycar/Screen1:Lit108	Lgnu/mapping/SimpleSymbol;
    //   1804: getstatic 983	appinventor/ai_prafulmathur95/whereismycar/Screen1:lambda$Fn27	Lgnu/expr/ModuleMethod;
    //   1807: invokevirtual 1610	appinventor/ai_prafulmathur95/whereismycar/Screen1:addToComponents	(Ljava/lang/Object;Ljava/lang/Object;Ljava/lang/Object;Ljava/lang/Object;)V
    //   1810: goto -928 -> 882
    //   1813: aload_0
    //   1814: getstatic 864	appinventor/ai_prafulmathur95/whereismycar/Screen1:Lit0	Lgnu/mapping/SimpleSymbol;
    //   1817: getstatic 535	appinventor/ai_prafulmathur95/whereismycar/Screen1:Lit113	Lgnu/lists/FString;
    //   1820: getstatic 538	appinventor/ai_prafulmathur95/whereismycar/Screen1:Lit112	Lgnu/mapping/SimpleSymbol;
    //   1823: getstatic 1316	java/lang/Boolean:FALSE	Ljava/lang/Boolean;
    //   1826: invokevirtual 1610	appinventor/ai_prafulmathur95/whereismycar/Screen1:addToComponents	(Ljava/lang/Object;Ljava/lang/Object;Ljava/lang/Object;Ljava/lang/Object;)V
    //   1829: goto -914 -> 915
    //   1832: aload_0
    //   1833: getstatic 538	appinventor/ai_prafulmathur95/whereismycar/Screen1:Lit112	Lgnu/mapping/SimpleSymbol;
    //   1836: getstatic 526	appinventor/ai_prafulmathur95/whereismycar/Screen1:Lit117	Lgnu/lists/FString;
    //   1839: getstatic 531	appinventor/ai_prafulmathur95/whereismycar/Screen1:Lit115	Lgnu/mapping/SimpleSymbol;
    //   1842: getstatic 987	appinventor/ai_prafulmathur95/whereismycar/Screen1:lambda$Fn29	Lgnu/expr/ModuleMethod;
    //   1845: invokevirtual 1610	appinventor/ai_prafulmathur95/whereismycar/Screen1:addToComponents	(Ljava/lang/Object;Ljava/lang/Object;Ljava/lang/Object;Ljava/lang/Object;)V
    //   1848: goto -900 -> 948
    //   1851: aload_0
    //   1852: getstatic 538	appinventor/ai_prafulmathur95/whereismycar/Screen1:Lit112	Lgnu/mapping/SimpleSymbol;
    //   1855: getstatic 520	appinventor/ai_prafulmathur95/whereismycar/Screen1:Lit120	Lgnu/lists/FString;
    //   1858: getstatic 779	appinventor/ai_prafulmathur95/whereismycar/Screen1:Lit24	Lgnu/mapping/SimpleSymbol;
    //   1861: getstatic 991	appinventor/ai_prafulmathur95/whereismycar/Screen1:lambda$Fn31	Lgnu/expr/ModuleMethod;
    //   1864: invokevirtual 1610	appinventor/ai_prafulmathur95/whereismycar/Screen1:addToComponents	(Ljava/lang/Object;Ljava/lang/Object;Ljava/lang/Object;Ljava/lang/Object;)V
    //   1867: goto -886 -> 981
    //   1870: aload_0
    //   1871: getstatic 864	appinventor/ai_prafulmathur95/whereismycar/Screen1:Lit0	Lgnu/mapping/SimpleSymbol;
    //   1874: getstatic 513	appinventor/ai_prafulmathur95/whereismycar/Screen1:Lit123	Lgnu/lists/FString;
    //   1877: getstatic 516	appinventor/ai_prafulmathur95/whereismycar/Screen1:Lit122	Lgnu/mapping/SimpleSymbol;
    //   1880: getstatic 1316	java/lang/Boolean:FALSE	Ljava/lang/Boolean;
    //   1883: invokevirtual 1610	appinventor/ai_prafulmathur95/whereismycar/Screen1:addToComponents	(Ljava/lang/Object;Ljava/lang/Object;Ljava/lang/Object;Ljava/lang/Object;)V
    //   1886: goto -872 -> 1014
    //   1889: aload_0
    //   1890: getstatic 516	appinventor/ai_prafulmathur95/whereismycar/Screen1:Lit122	Lgnu/mapping/SimpleSymbol;
    //   1893: getstatic 502	appinventor/ai_prafulmathur95/whereismycar/Screen1:Lit127	Lgnu/lists/FString;
    //   1896: getstatic 507	appinventor/ai_prafulmathur95/whereismycar/Screen1:Lit125	Lgnu/mapping/SimpleSymbol;
    //   1899: getstatic 995	appinventor/ai_prafulmathur95/whereismycar/Screen1:lambda$Fn33	Lgnu/expr/ModuleMethod;
    //   1902: invokevirtual 1610	appinventor/ai_prafulmathur95/whereismycar/Screen1:addToComponents	(Ljava/lang/Object;Ljava/lang/Object;Ljava/lang/Object;Ljava/lang/Object;)V
    //   1905: goto -858 -> 1047
    //   1908: aload_0
    //   1909: getstatic 516	appinventor/ai_prafulmathur95/whereismycar/Screen1:Lit122	Lgnu/mapping/SimpleSymbol;
    //   1912: getstatic 496	appinventor/ai_prafulmathur95/whereismycar/Screen1:Lit130	Lgnu/lists/FString;
    //   1915: getstatic 772	appinventor/ai_prafulmathur95/whereismycar/Screen1:Lit26	Lgnu/mapping/SimpleSymbol;
    //   1918: getstatic 999	appinventor/ai_prafulmathur95/whereismycar/Screen1:lambda$Fn35	Lgnu/expr/ModuleMethod;
    //   1921: invokevirtual 1610	appinventor/ai_prafulmathur95/whereismycar/Screen1:addToComponents	(Ljava/lang/Object;Ljava/lang/Object;Ljava/lang/Object;Ljava/lang/Object;)V
    //   1924: goto -844 -> 1080
    //   1927: aload_0
    //   1928: getstatic 516	appinventor/ai_prafulmathur95/whereismycar/Screen1:Lit122	Lgnu/mapping/SimpleSymbol;
    //   1931: getstatic 487	appinventor/ai_prafulmathur95/whereismycar/Screen1:Lit134	Lgnu/lists/FString;
    //   1934: getstatic 492	appinventor/ai_prafulmathur95/whereismycar/Screen1:Lit132	Lgnu/mapping/SimpleSymbol;
    //   1937: getstatic 1003	appinventor/ai_prafulmathur95/whereismycar/Screen1:lambda$Fn37	Lgnu/expr/ModuleMethod;
    //   1940: invokevirtual 1610	appinventor/ai_prafulmathur95/whereismycar/Screen1:addToComponents	(Ljava/lang/Object;Ljava/lang/Object;Ljava/lang/Object;Ljava/lang/Object;)V
    //   1943: goto -830 -> 1113
    //   1946: aload_0
    //   1947: getstatic 516	appinventor/ai_prafulmathur95/whereismycar/Screen1:Lit122	Lgnu/mapping/SimpleSymbol;
    //   1950: getstatic 476	appinventor/ai_prafulmathur95/whereismycar/Screen1:Lit137	Lgnu/lists/FString;
    //   1953: getstatic 762	appinventor/ai_prafulmathur95/whereismycar/Screen1:Lit29	Lgnu/mapping/SimpleSymbol;
    //   1956: getstatic 1007	appinventor/ai_prafulmathur95/whereismycar/Screen1:lambda$Fn39	Lgnu/expr/ModuleMethod;
    //   1959: invokevirtual 1610	appinventor/ai_prafulmathur95/whereismycar/Screen1:addToComponents	(Ljava/lang/Object;Ljava/lang/Object;Ljava/lang/Object;Ljava/lang/Object;)V
    //   1962: goto -816 -> 1146
    //   1965: aload_0
    //   1966: getstatic 864	appinventor/ai_prafulmathur95/whereismycar/Screen1:Lit0	Lgnu/mapping/SimpleSymbol;
    //   1969: getstatic 470	appinventor/ai_prafulmathur95/whereismycar/Screen1:Lit139	Lgnu/lists/FString;
    //   1972: getstatic 752	appinventor/ai_prafulmathur95/whereismycar/Screen1:Lit32	Lgnu/mapping/SimpleSymbol;
    //   1975: getstatic 1011	appinventor/ai_prafulmathur95/whereismycar/Screen1:lambda$Fn41	Lgnu/expr/ModuleMethod;
    //   1978: invokevirtual 1610	appinventor/ai_prafulmathur95/whereismycar/Screen1:addToComponents	(Ljava/lang/Object;Ljava/lang/Object;Ljava/lang/Object;Ljava/lang/Object;)V
    //   1981: goto -802 -> 1179
    //   1984: aload_0
    //   1985: getstatic 414	appinventor/ai_prafulmathur95/whereismycar/Screen1:Lit147	Lgnu/mapping/SimpleSymbol;
    //   1988: aload_0
    //   1989: getfield 1017	appinventor/ai_prafulmathur95/whereismycar/Screen1:directionbutton$Click	Lgnu/expr/ModuleMethod;
    //   1992: invokevirtual 1228	appinventor/ai_prafulmathur95/whereismycar/Screen1:addToFormEnvironment	(Lgnu/mapping/Symbol;Ljava/lang/Object;)V
    //   1995: goto -796 -> 1199
    //   1998: aload_0
    //   1999: getstatic 752	appinventor/ai_prafulmathur95/whereismycar/Screen1:Lit32	Lgnu/mapping/SimpleSymbol;
    //   2002: getstatic 553	appinventor/ai_prafulmathur95/whereismycar/Screen1:Lit106	Lgnu/mapping/SimpleSymbol;
    //   2005: invokevirtual 1608	appinventor/ai_prafulmathur95/whereismycar/Screen1:addToEvents	(Ljava/lang/Object;Ljava/lang/Object;)V
    //   2008: goto -785 -> 1223
    //   2011: aload_0
    //   2012: getstatic 864	appinventor/ai_prafulmathur95/whereismycar/Screen1:Lit0	Lgnu/mapping/SimpleSymbol;
    //   2015: getstatic 409	appinventor/ai_prafulmathur95/whereismycar/Screen1:Lit149	Lgnu/lists/FString;
    //   2018: getstatic 810	appinventor/ai_prafulmathur95/whereismycar/Screen1:Lit16	Lgnu/mapping/SimpleSymbol;
    //   2021: getstatic 1316	java/lang/Boolean:FALSE	Ljava/lang/Boolean;
    //   2024: invokevirtual 1610	appinventor/ai_prafulmathur95/whereismycar/Screen1:addToComponents	(Ljava/lang/Object;Ljava/lang/Object;Ljava/lang/Object;Ljava/lang/Object;)V
    //   2027: goto -771 -> 1256
    //   2030: aload_0
    //   2031: getstatic 405	appinventor/ai_prafulmathur95/whereismycar/Screen1:Lit150	Lgnu/mapping/SimpleSymbol;
    //   2034: aload_0
    //   2035: getfield 1019	appinventor/ai_prafulmathur95/whereismycar/Screen1:LocationSensor1$LocationChanged	Lgnu/expr/ModuleMethod;
    //   2038: invokevirtual 1228	appinventor/ai_prafulmathur95/whereismycar/Screen1:addToFormEnvironment	(Lgnu/mapping/Symbol;Ljava/lang/Object;)V
    //   2041: goto -765 -> 1276
    //   2044: aload_0
    //   2045: getstatic 810	appinventor/ai_prafulmathur95/whereismycar/Screen1:Lit16	Lgnu/mapping/SimpleSymbol;
    //   2048: getstatic 402	appinventor/ai_prafulmathur95/whereismycar/Screen1:Lit151	Lgnu/mapping/SimpleSymbol;
    //   2051: invokevirtual 1608	appinventor/ai_prafulmathur95/whereismycar/Screen1:addToEvents	(Ljava/lang/Object;Ljava/lang/Object;)V
    //   2054: goto -754 -> 1300
    //   2057: aload_0
    //   2058: getstatic 864	appinventor/ai_prafulmathur95/whereismycar/Screen1:Lit0	Lgnu/mapping/SimpleSymbol;
    //   2061: getstatic 384	appinventor/ai_prafulmathur95/whereismycar/Screen1:Lit156	Lgnu/lists/FString;
    //   2064: getstatic 458	appinventor/ai_prafulmathur95/whereismycar/Screen1:Lit142	Lgnu/mapping/SimpleSymbol;
    //   2067: getstatic 1023	appinventor/ai_prafulmathur95/whereismycar/Screen1:lambda$Fn45	Lgnu/expr/ModuleMethod;
    //   2070: invokevirtual 1610	appinventor/ai_prafulmathur95/whereismycar/Screen1:addToComponents	(Ljava/lang/Object;Ljava/lang/Object;Ljava/lang/Object;Ljava/lang/Object;)V
    //   2073: goto -740 -> 1333
    //   2076: aload_0
    //   2077: getstatic 864	appinventor/ai_prafulmathur95/whereismycar/Screen1:Lit0	Lgnu/mapping/SimpleSymbol;
    //   2080: getstatic 378	appinventor/ai_prafulmathur95/whereismycar/Screen1:Lit158	Lgnu/lists/FString;
    //   2083: getstatic 803	appinventor/ai_prafulmathur95/whereismycar/Screen1:Lit18	Lgnu/mapping/SimpleSymbol;
    //   2086: getstatic 1316	java/lang/Boolean:FALSE	Ljava/lang/Boolean;
    //   2089: invokevirtual 1610	appinventor/ai_prafulmathur95/whereismycar/Screen1:addToComponents	(Ljava/lang/Object;Ljava/lang/Object;Ljava/lang/Object;Ljava/lang/Object;)V
    //   2092: goto -726 -> 1366
    //   2095: aload_0
    //   2096: getstatic 864	appinventor/ai_prafulmathur95/whereismycar/Screen1:Lit0	Lgnu/mapping/SimpleSymbol;
    //   2099: getstatic 374	appinventor/ai_prafulmathur95/whereismycar/Screen1:Lit160	Lgnu/lists/FString;
    //   2102: getstatic 769	appinventor/ai_prafulmathur95/whereismycar/Screen1:Lit27	Lgnu/mapping/SimpleSymbol;
    //   2105: getstatic 1316	java/lang/Boolean:FALSE	Ljava/lang/Boolean;
    //   2108: invokevirtual 1610	appinventor/ai_prafulmathur95/whereismycar/Screen1:addToComponents	(Ljava/lang/Object;Ljava/lang/Object;Ljava/lang/Object;Ljava/lang/Object;)V
    //   2111: goto -712 -> 1399
    //   2114: aload_0
    //   2115: getstatic 864	appinventor/ai_prafulmathur95/whereismycar/Screen1:Lit0	Lgnu/mapping/SimpleSymbol;
    //   2118: getstatic 370	appinventor/ai_prafulmathur95/whereismycar/Screen1:Lit162	Lgnu/lists/FString;
    //   2121: getstatic 759	appinventor/ai_prafulmathur95/whereismycar/Screen1:Lit30	Lgnu/mapping/SimpleSymbol;
    //   2124: getstatic 1316	java/lang/Boolean:FALSE	Ljava/lang/Boolean;
    //   2127: invokevirtual 1610	appinventor/ai_prafulmathur95/whereismycar/Screen1:addToComponents	(Ljava/lang/Object;Ljava/lang/Object;Ljava/lang/Object;Ljava/lang/Object;)V
    //   2130: goto -698 -> 1432
    //   2133: astore_2
    //   2134: new 1107	gnu/mapping/WrongType
    //   2137: dup
    //   2138: aload_2
    //   2139: ldc_w 1612
    //   2142: iconst_1
    //   2143: aload_1
    //   2144: invokespecial 1112	gnu/mapping/WrongType:<init>	(Ljava/lang/ClassCastException;Ljava/lang/String;ILjava/lang/Object;)V
    //   2147: athrow
    //   2148: astore_2
    //   2149: new 1107	gnu/mapping/WrongType
    //   2152: dup
    //   2153: aload_2
    //   2154: ldc_w 1612
    //   2157: iconst_1
    //   2158: aload_1
    //   2159: invokespecial 1112	gnu/mapping/WrongType:<init>	(Ljava/lang/ClassCastException;Ljava/lang/String;ILjava/lang/Object;)V
    //   2162: athrow
    // Local variable table:
    //   start	length	slot	name	signature
    //   0	2163	0	this	Screen1
    //   0	2163	1	paramCallContext	CallContext
    //   4	1425	2	localConsumer	Consumer
    //   2133	6	2	localClassCastException1	ClassCastException
    //   2148	6	2	localClassCastException2	ClassCastException
    //   16	116	3	localRunnable	Runnable
    // Exception table:
    //   from	to	target	type
    //   12	17	2133	java/lang/ClassCastException
    //   126	131	2148	java/lang/ClassCastException
  }
  
  public void sendError(Object paramObject)
  {
    if (paramObject == null) {}
    for (paramObject = null;; paramObject = paramObject.toString())
    {
      RetValManager.sendError((String)paramObject);
      return;
    }
  }
}


/* Location:              C:\Users\User\Desktop\dex2jar-2.0\classes-dex2jar.jar!\appinventor\ai_prafulmathur95\whereismycar\Screen1.class
 * Java compiler version: 6 (50.0)
 * JD-Core Version:       0.7.1
 */